Workbook

Sheet Cómo usar
A1: Planilla de Avonlea
A2: Generada el 2026-10-19 12:50 desde los datos del juego (node tools/planilla.js).
A4: Qué se edita (las celdas amarillas claras)
A5: • «Frases»: lo que dice cada uno al pasar. Una fila por frase: quién, el tipo (dice / ana / una estación), el texto y cuándo vale.
A6: ¿Conoce a Ana?: sí (solo después de presentarse), no (solo antes), o vacío. «Después de»: un hecho o una meta (lista); con «Días después», desde N días después.
A7: «Antes de»: solo mientras ese hecho o meta no pasó. «Estación»: solo esa estación. «Otras condiciones»: cualquier otra, tal cual, con comas.
A8: Para agregar una frase, una fila nueva al final; para quitarla, borra la fila.
A9: • «Escenas»: cuándo empieza cada escena del guion y qué deja (canal, prioridad, condiciones, dónde, quiénes, el cartel, las acciones al empezar y al terminar).
A10: Los campos que se repiten (por ejemplo, «Al terminar») van uno por línea dentro de la celda (Alt+Enter). Lo que dicen está en la hoja «Diálogos» y se edita en src/datos/guion.txt.
A11: Las escenas nuevas se escriben en src/datos/guion.txt (con sus líneas); aquí se cambian las que hay.
A12: • «Noticias»: quién sabe cada noticia, a quién le llega, cuánto se cuenta, cómo se cuenta y sus versiones exageradas. Una fila nueva es una noticia nueva.
A13: • «Llegadas»: cuándo llega y se va cada uno (una alternativa por línea), si viene de visita, y lo que queda en el diario. Una fila nueva es alguien que llega.
... A29: • «Personas», «Hechos» (quién deja y quién pide cada hecho; rojo: nunca pasa; amarillo: nadie lo lee), «Metas» (el cuaderno de Ana).

Sheet Frases
A1: Quién | B1: Nombre | C1: Tipo | D1: Frase | E1: ¿Conoce a Ana? | F1: Después de (hecho o meta) | G1: Días después | H1: Antes de (hecho o meta) | I1: Estación | J1: Otras condiciones
A2: matthew | B2: =IFERROR(INDEX(Personas!$B:$B,MATCH(A2,Personas!$A:$A,0)),"(¿quién?)") | C2: dice | D2: (Matthew se pone colorado y mira para otro lado.) Bueno, pues… quizás… ¿no tienes frío, Ana? | J2: ana:camison, !donde:ana:tejas
A3: matthew | B3: =IFERROR(INDEX(Personas!$B:$B,MATCH(A3,Personas!$A:$A,0)),"(¿quién?)") | C3: dice | D3: Bueno, pues… es tarde, Ana. Marilla se va a preocupar. Te acompaño, ¿sí? | J3: hora:21-26, !donde:ana:tejas
A4: matthew | B4: =IFERROR(INDEX(Personas!$B:$B,MATCH(A4,Personas!$A:$A,0)),"(¿quién?)") | C4: dice | D4: Bueno, pues... Marilla es buena, ¿sabes? Solo que no se le nota mucho al principio. | H4: se_queda
A5: matthew | B5: =IFERROR(INDEX(Personas!$B:$B,MATCH(A5,Personas!$A:$A,0)),"(¿quién?)") | C5: dice | D5: Ya lo creo que... bueno, ojalá te quedes, Ana. Yo... sí. Eso. | H5: se_queda
A6: matthew | B6: =IFERROR(INDEX(Personas!$B:$B,MATCH(A6,Personas!$A:$A,0)),"(¿quién?)") | C6: dice | D6: Bueno, pues... sí, es un día precioso, Ana. Ya lo creo.
A7: matthew | B7: =IFERROR(INDEX(Personas!$B:$B,MATCH(A7,Personas!$A:$A,0)),"(¿quién?)") | C7: dice | D7: Las vacas andan contentas hoy. Será por el sol, supongo.
A8: matthew | B8: =IFERROR(INDEX(Personas!$B:$B,MATCH(A8,Personas!$A:$A,0)),"(¿quién?)") | C8: dice | D8: Marilla dice que hablas mucho. Bueno, a mí me gusta oírte, ¿sabes? | F8: se_queda
A9: matthew | B9: =IFERROR(INDEX(Personas!$B:$B,MATCH(A9,Personas!$A:$A,0)),"(¿quién?)") | C9: dice | D9: ¿Viste las flores junto al camino? Bueno, pues... me hicieron pensar en ti. | F9: se_queda
A10: matthew | B10: =IFERROR(INDEX(Personas!$B:$B,MATCH(A10,Personas!$A:$A,0)),"(¿quién?)") | C10: dice | D10: Ya lo creo, ya lo creo. Anda, ve a jugar un rato, que el día está lindo. | F10: se_queda
A11: matthew | B11: =IFERROR(INDEX(Personas!$B:$B,MATCH(A11,Personas!$A:$A,0)),"(¿quién?)") | C11: primavera | D11: Bueno, pues... ya brotó todo. La primavera, ¿no? Ya lo creo.
A12: matthew | B12: =IFERROR(INDEX(Personas!$B:$B,MATCH(A12,Personas!$A:$A,0)),"(¿quién?)") | C12: verano | D12: Hace calor para la siega, ya lo creo. Bueno, el heno no se corta solo.
A13: matthew | B13: =IFERROR(INDEX(Personas!$B:$B,MATCH(A13,Personas!$A:$A,0)),"(¿quién?)") | C13: otoño | D13: Las manzanas de los Barry están en su punto. Marilla querrá hacer compota, supongo.
A14: matthew | B14: =IFERROR(INDEX(Personas!$B:$B,MATCH(A14,Personas!$A:$A,0)),"(¿quién?)") | C14: invierno | D14: Abrígate bien, Ana. El frío... bueno, pues, no es broma.
A15: marilla | B15: =IFERROR(INDEX(Personas!$B:$B,MATCH(A15,Personas!$A:$A,0)),"(¿quién?)") | C15: dice | D15: ¡Ana Shirley! ¡A casa ahora mismo, y te vistes como una persona decente! | J15: ana:camison, !donde:ana:tejas
A16: marilla | B16: =IFERROR(INDEX(Personas!$B:$B,MATCH(A16,Personas!$A:$A,0)),"(¿quién?)") | C16: dice | D16: ¿Qué haces afuera a estas horas? ¡A casa, y sin chistar! | J16: hora:21-26, !donde:ana:tejas
A17: marilla | B17: =IFERROR(INDEX(Personas!$B:$B,MATCH(A17,Personas!$A:$A,0)),"(¿quién?)") | C17: dice | D17: (Marilla le susurra, sin mover los labios.) ¿Y tu sombrero? ¡En la iglesia! | J17: ana:sin_sombrero, escena_ana:ig
A18: marilla | B18: =IFERROR(INDEX(Personas!$B:$B,MATCH(A18,Personas!$A:$A,0)),"(¿quién?)") | C18: dice | D18: Mientras estés en esta casa, harás tus quehaceres como cualquiera. Después veremos. | H18: se_queda
A19: marilla | B19: =IFERROR(INDEX(Personas!$B:$B,MATCH(A19,Personas!$A:$A,0)),"(¿quién?)") | C19: dice | D19: No te prometo nada, niña. Que te quedes o no, depende de cómo te portes. | H19: se_queda
A20: marilla | B20: =IFERROR(INDEX(Personas!$B:$B,MATCH(A20,Personas!$A:$A,0)),"(¿quién?)") | C20: dice | D20: Lávate la cara y péinate esas trenzas. Aquí se come con la cara limpia. | H20: se_queda
A21: marilla | B21: =IFERROR(INDEX(Personas!$B:$B,MATCH(A21,Personas!$A:$A,0)),"(¿quién?)") | C21: dice | D21: ¿Sabes rezar? Pues vas a aprender. En esta casa se reza. | H21: se_queda | J21: !dicha:conv_marilla_oraciones
A22: marilla | B22: =IFERROR(INDEX(Personas!$B:$B,MATCH(A22,Personas!$A:$A,0)),"(¿quién?)") | C22: dice | D22: Ana, no te quedes soñando despierta. Aunque... la cocina está ordenada, eso sí. | F22: se_queda
A23: marilla | B23: =IFERROR(INDEX(Personas!$B:$B,MATCH(A23,Personas!$A:$A,0)),"(¿quién?)") | C23: dice | D23: Si quieres cocinar, la estufa está encendida. Cuidado con no quemar nada. | F23: se_queda
A24: marilla | B24: =IFERROR(INDEX(Personas!$B:$B,MATCH(A24,Personas!$A:$A,0)),"(¿quién?)") | C24: dice | D24: Matthew no lo dice, pero te echa de menos cuando te vas donde Diana. | F24: se_queda | J24: hecho:conocidas_diana
A25: marilla | B25: =IFERROR(INDEX(Personas!$B:$B,MATCH(A25,Personas!$A:$A,0)),"(¿quién?)") | C25: dice | D25: Riega la huerta antes de que caiga el sol, que las plantas lo agradecen. La regadera está junto a la bomba. | F25: se_queda | J25: hora:12-18, no_hoy:regado
A26: marilla | B26: =IFERROR(INDEX(Personas!$B:$B,MATCH(A26,Personas!$A:$A,0)),"(¿quién?)") | C26: dice | D26: Hmm. Bueno, admito que hoy te has portado muy bien. | F26: se_queda | J26: afecto:marilla:ana>=3
A27: marilla | B27: =IFERROR(INDEX(Personas!$B:$B,MATCH(A27,Personas!$A:$A,0)),"(¿quién?)") | C27: dice | D27: Ese vestido parece que durmió en el suelo, Ana. Ah, claro: es que durmió en el suelo. | F27: ropa_arrugada | H27: ropa_ordenada
A28: marilla | B28: =IFERROR(INDEX(Personas!$B:$B,MATCH(A28,Personas!$A:$A,0)),"(¿quién?)") | C28: primavera | D28: Hay que limpiar la casa a fondo, que es primavera. Y tú me vas a ayudar, Ana. | F28: se_queda
A29: marilla | B29: =IFERROR(INDEX(Personas!$B:$B,MATCH(A29,Personas!$A:$A,0)),"(¿quién?)") | C29: verano | D29: Con este calor, mejor un té y no enciendas mucho la estufa.
A30: marilla | B30: =IFERROR(INDEX(Personas!$B:$B,MATCH(A30,Personas!$A:$A,0)),"(¿quién?)") | C30: otoño | D30: Es tiempo de manzanas: una buena compota para el invierno no está de más.
A31: marilla | B31: =IFERROR(INDEX(Personas!$B:$B,MATCH(A31,Personas!$A:$A,0)),"(¿quién?)") | C31: invierno | D31: Siéntate cerca de la estufa, niña, que vienes helada.
A32: diana | B32: =IFERROR(INDEX(Personas!$B:$B,MATCH(A32,Personas!$A:$A,0)),"(¿quién?)") | C32: dice | D32: ¡Ana! ¿Saliste así? ¡Ven, te presto mi chal antes de que te vea mamá! | J32: ana:camison, !donde:ana:tejas
A33: diana | B33: =IFERROR(INDEX(Personas!$B:$B,MATCH(A33,Personas!$A:$A,0)),"(¿quién?)") | C33: dice | D33: (Diana le pasa su pañuelo, a escondidas.) Póntelo en la cabeza, rápido. | J33: ana:sin_sombrero, escena_ana:ig
A34: diana | B34: =IFERROR(INDEX(Personas!$B:$B,MATCH(A34,Personas!$A:$A,0)),"(¿quién?)") | C34: dice | D34: ¡Ana! ¿Qué haces afuera a esta hora? Si mamá te ve, no me deja verte nunca más. | J34: hora:21-26, !donde:ana:tejas
A35: diana | B35: =IFERROR(INDEX(Personas!$B:$B,MATCH(A35,Personas!$A:$A,0)),"(¿quién?)") | C35: dice | D35: ¡Ana, mi alma gemela! Te estaba esperando. | F35: conocidas_diana | G35: 2 | H35: prohibida
A36: diana | B36: =IFERROR(INDEX(Personas!$B:$B,MATCH(A36,Personas!$A:$A,0)),"(¿quién?)") | C36: dice | D36: Mamá dice que puedo salir hasta que se ponga el sol. ¿Vamos al lago? | F36: conocidas_diana | H36: prohibida
A37: diana | B37: =IFERROR(INDEX(Personas!$B:$B,MATCH(A37,Personas!$A:$A,0)),"(¿quién?)") | C37: dice | D37: ¿Te acuerdas de nuestro juramento de amistad? ¡Para siempre! | F37: conocidas_diana | H37: prohibida | J37: cuaderno:amigas, afecto:diana:ana>=4
A38: diana | B38: =IFERROR(INDEX(Personas!$B:$B,MATCH(A38,Personas!$A:$A,0)),"(¿quién?)") | C38: dice | D38: Los manzanos están llenos este año. Toma las que quieras. | F38: conocidas_diana | H38: prohibida
A39: diana | B39: =IFERROR(INDEX(Personas!$B:$B,MATCH(A39,Personas!$A:$A,0)),"(¿quién?)") | C39: dice | D39: El Bosque Encantado me da un poquito de miedo... pero contigo no. | F39: conocidas_diana | H39: prohibida
A40: diana | B40: =IFERROR(INDEX(Personas!$B:$B,MATCH(A40,Personas!$A:$A,0)),"(¿quién?)") | C40: dice | D40: Hola. Tú eres la niña nueva de Tejas Verdes, ¿verdad? | H40: conocidas_diana
A41: diana | B41: =IFERROR(INDEX(Personas!$B:$B,MATCH(A41,Personas!$A:$A,0)),"(¿quién?)") | C41: dice | D41: (Diana baja la vista.) Mamá dice que no puedo hablar contigo, Ana... Lo siento tanto. | F41: prohibida
A42: diana | B42: =IFERROR(INDEX(Personas!$B:$B,MATCH(A42,Personas!$A:$A,0)),"(¿quién?)") | C42: primavera | D42: ¡Mira los manzanos en flor, Ana! Parecen novias vestidas de blanco. | F42: conocidas_diana | H42: prohibida
A43: diana | B43: =IFERROR(INDEX(Personas!$B:$B,MATCH(A43,Personas!$A:$A,0)),"(¿quién?)") | C43: verano | D43: ¡Qué calor! ¿Vamos a remojar los pies en el lago? | F43: conocidas_diana | H43: prohibida
A44: diana | B44: =IFERROR(INDEX(Personas!$B:$B,MATCH(A44,Personas!$A:$A,0)),"(¿quién?)") | C44: otoño | D44: El Bosque Encantado está todo rojo y dorado... ¡como un cuento! | F44: conocidas_diana | H44: prohibida
A45: diana | B45: =IFERROR(INDEX(Personas!$B:$B,MATCH(A45,Personas!$A:$A,0)),"(¿quién?)") | C45: invierno | D45: ¡Está nevando! Mamá no me deja salir sin bufanda. Ven, entra a calentarte junto al fuego. | F45: conocidas_diana | H45: prohibida
A46: barry | B46: =IFERROR(INDEX(Personas!$B:$B,MATCH(A46,Personas!$A:$A,0)),"(¿quién?)") | C46: dice | D46: Tú debes ser la niña que trajeron los Cuthbert. Buenas tardes. | E46: no | H46: barry_presenta | J46: sabe:barry:nina_cuthbert
A47: barry | B47: =IFERROR(INDEX(Personas!$B:$B,MATCH(A47,Personas!$A:$A,0)),"(¿quién?)") | C47: dice | D47: Ana Shirley, siempre es un gusto verte por aquí. Pórtate bien, ¿eh? | F47: barry_presenta | H47: prohibida
A48: barry | B48: =IFERROR(INDEX(Personas!$B:$B,MATCH(A48,Personas!$A:$A,0)),"(¿quién?)") | C48: dice | D48: Diana habla de ti todo el día, ¿sabes? | F48: conocidas_diana | G48: 3 | H48: prohibida
A49: barry | B49: =IFERROR(INDEX(Personas!$B:$B,MATCH(A49,Personas!$A:$A,0)),"(¿quién?)") | C49: dice | D49: Esta vez el cordial de frambuesa está bien etiquetado, te lo aseguro. | F49: perdonada
A50: barry | B50: =IFERROR(INDEX(Personas!$B:$B,MATCH(A50,Personas!$A:$A,0)),"(¿quién?)") | C50: dice | D50: Buenas tardes. (La Sra. Barry no la invita a pasar.) | F50: prohibida | H50: perdonada
A51: barry | B51: =IFERROR(INDEX(Personas!$B:$B,MATCH(A51,Personas!$A:$A,0)),"(¿quién?)") | C51: dice | D51: Saluda a Marilla de mi parte. | H51: prohibida | J51: !donde:ana:tejas
A52: barry | B52: =IFERROR(INDEX(Personas!$B:$B,MATCH(A52,Personas!$A:$A,0)),"(¿quién?)") | C52: dice | D52: Buenos días, niña. ¿Y Marilla, cómo está? Hace tiempo que no la veo. | E52: sí | H52: barry_presenta
A53: barry | B53: =IFERROR(INDEX(Personas!$B:$B,MATCH(A53,Personas!$A:$A,0)),"(¿quién?)") | C53: primavera | D53: Buenos días, Ana. Diana está deseando verte. | F53: barry_presenta | H53: prohibida
A54: barry | B54: =IFERROR(INDEX(Personas!$B:$B,MATCH(A54,Personas!$A:$A,0)),"(¿quién?)") | C54: verano | D54: Qué calor, ¿verdad? Hay limonada en la despensa. | F54: barry_presenta | H54: prohibida
A55: barry | B55: =IFERROR(INDEX(Personas!$B:$B,MATCH(A55,Personas!$A:$A,0)),"(¿quién?)") | C55: otoño | D55: Diana me ayudó con las manzanas. Llévale algunas a Marilla. | F55: barry_presenta | H55: prohibida
A56: barry | B56: =IFERROR(INDEX(Personas!$B:$B,MATCH(A56,Personas!$A:$A,0)),"(¿quién?)") | C56: invierno | D56: Pasa, pasa, que hace un frío terrible. Diana está junto al fuego. | F56: barry_presenta | H56: prohibida | J56: escena_ana:os
A57: lynde | B57: =IFERROR(INDEX(Personas!$B:$B,MATCH(A57,Personas!$A:$A,0)),"(¿quién?)") | C57: dice | D57: ¿Así que tú eres la huérfana de Tejas Verdes? Ya iré a verte con calma, ya. | E57: no | H57: lynde_visita | J57: sabe:lynde:nina_cuthbert
A58: lynde | B58: =IFERROR(INDEX(Personas!$B:$B,MATCH(A58,Personas!$A:$A,0)),"(¿quién?)") | C58: dice | D58: Hmpf. No tengo nada que hablar contigo, niña malcriada. | F58: ofendio_lynde | H58: disculpa_lynde
A59: lynde | B59: =IFERROR(INDEX(Personas!$B:$B,MATCH(A59,Personas!$A:$A,0)),"(¿quién?)") | C59: dice | D59: Desde mi ventana veo todo el camino: no se me escapa nadie. Lo digo sin mala intención, ¿eh? | H59: ofendio_lynde
A60: lynde | B60: =IFERROR(INDEX(Personas!$B:$B,MATCH(A60,Personas!$A:$A,0)),"(¿quién?)") | C60: dice | D60: Llevo cincuenta y dos cubrecamas de retazos, ¡cincuenta y dos! Y no pienso parar. | H60: ofendio_lynde
A61: lynde | B61: =IFERROR(INDEX(Personas!$B:$B,MATCH(A61,Personas!$A:$A,0)),"(¿quién?)") | C61: dice | D61: Marilla hizo bien en quedarse contigo, y lo digo yo, que nunca me callo lo que pienso. | F61: se_queda | H61: ofendio_lynde | J61: hecho:lynde_visita
A62: lynde | B62: =IFERROR(INDEX(Personas!$B:$B,MATCH(A62,Personas!$A:$A,0)),"(¿quién?)") | C62: dice | D62: A una niña hay que enseñarle a ser útil. Pero, bueno, tú vas por buen camino. | F62: lynde_visita | H62: ofendio_lynde
A63: lynde | B63: =IFERROR(INDEX(Personas!$B:$B,MATCH(A63,Personas!$A:$A,0)),"(¿quién?)") | C63: dice | D63: Ana Shirley, hablas más que un molino... pero tienes buen corazón, eso lo reconozco. | F63: lynde_visita | H63: ofendio_lynde
A64: lynde | B64: =IFERROR(INDEX(Personas!$B:$B,MATCH(A64,Personas!$A:$A,0)),"(¿quién?)") | C64: primavera | D64: ¡Vaya, vaya, ya brotó todo! Ya es hora de limpiar la casa, digo yo. | F64: lynde_visita | H64: ofendio_lynde
A65: lynde | B65: =IFERROR(INDEX(Personas!$B:$B,MATCH(A65,Personas!$A:$A,0)),"(¿quién?)") | C65: verano | D65: Con este calor no hay quien teja... ¡pero yo tejo, claro que tejo! | F65: lynde_visita | H65: ofendio_lynde
A66: lynde | B66: =IFERROR(INDEX(Personas!$B:$B,MATCH(A66,Personas!$A:$A,0)),"(¿quién?)") | C66: otoño | D66: El otoño siempre me hace pensar en los cubrecamas. Este año haré uno rojo y dorado. | F66: lynde_visita | H66: ofendio_lynde
A67: lynde | B67: =IFERROR(INDEX(Personas!$B:$B,MATCH(A67,Personas!$A:$A,0)),"(¿quién?)") | C67: invierno | D67: Pasa, niña, que hace un frío de mil demonios... perdón, de los que dan escalofríos. | F67: lynde_visita | H67: ofendio_lynde | J67: escena_ana:rl
A68: harrison | B68: =IFERROR(INDEX(Personas!$B:$B,MATCH(A68,Personas!$A:$A,0)),"(¿quién?)") | C68: dice | D68: ¡Hmpf! ¡En camisón! Ni Ginger anda tan mal vestido, muchacha. | J68: ana:camison, !donde:ana:tejas
A69: harrison | B69: =IFERROR(INDEX(Personas!$B:$B,MATCH(A69,Personas!$A:$A,0)),"(¿quién?)") | C69: dice | D69: ¿Tú, a esta hora? Vete a casa antes de que te confunda con un zorro. | J69: hora:21-26, !donde:ana:tejas
A70: harrison | B70: =IFERROR(INDEX(Personas!$B:$B,MATCH(A70,Personas!$A:$A,0)),"(¿quién?)") | C70: dice | D70: Hmpf. Buenos días... si es que son buenos.
A71: harrison | B71: =IFERROR(INDEX(Personas!$B:$B,MATCH(A71,Personas!$A:$A,0)),"(¿quién?)") | C71: dice | D71: ¿Esa vaca tuya se ha portado bien hoy? Más le vale. | F71: conoce_harrison | G71: 3
A72: harrison | B72: =IFERROR(INDEX(Personas!$B:$B,MATCH(A72,Personas!$A:$A,0)),"(¿quién?)") | C72: dice | D72: No me mires la casa, que el desorden es mío.
A73: harrison | B73: =IFERROR(INDEX(Personas!$B:$B,MATCH(A73,Personas!$A:$A,0)),"(¿quién?)") | C73: dice | D73: Ginger, ¡silencio!... No le hagas caso, muchacha.
A74: harrison | B74: =IFERROR(INDEX(Personas!$B:$B,MATCH(A74,Personas!$A:$A,0)),"(¿quién?)") | C74: primavera | D74: La avena ya asoma. Que nadie la pise, ¿eh?
A75: harrison | B75: =IFERROR(INDEX(Personas!$B:$B,MATCH(A75,Personas!$A:$A,0)),"(¿quién?)") | C75: verano | D75: Calor de mil demonios para segar... con perdón.
A76: harrison | B76: =IFERROR(INDEX(Personas!$B:$B,MATCH(A76,Personas!$A:$A,0)),"(¿quién?)") | C76: otoño | D76: Buena cosecha este año, aunque no lo diga mucho.
A77: harrison | B77: =IFERROR(INDEX(Personas!$B:$B,MATCH(A77,Personas!$A:$A,0)),"(¿quién?)") | C77: invierno | D77: Con este frío, ni Ginger quiere hablar. Bueno, sí quiere.
A78: shearer | B78: =IFERROR(INDEX(Personas!$B:$B,MATCH(A78,Personas!$A:$A,0)),"(¿quién?)") | C78: dice | D78: Buen día, señorita. ¿Algún animal para vender?
A79: shearer | B79: =IFERROR(INDEX(Personas!$B:$B,MATCH(A79,Personas!$A:$A,0)),"(¿quién?)") | C79: dice | D79: Ando apurado: me esperan en Carmody.
A80: shearer | B80: =IFERROR(INDEX(Personas!$B:$B,MATCH(A80,Personas!$A:$A,0)),"(¿quién?)") | C80: dice | D80: Buena tierra la de por aquí, sí señor.
A81: shearer | B81: =IFERROR(INDEX(Personas!$B:$B,MATCH(A81,Personas!$A:$A,0)),"(¿quién?)") | C81: primavera | D81: Primavera: buen tiempo para comprar terneros.
A82: shearer | B82: =IFERROR(INDEX(Personas!$B:$B,MATCH(A82,Personas!$A:$A,0)),"(¿quién?)") | C82: verano | D82: Con este calor las vacas dan menos leche, ¿sabía?
A83: shearer | B83: =IFERROR(INDEX(Personas!$B:$B,MATCH(A83,Personas!$A:$A,0)),"(¿quién?)") | C83: otoño | D83: En otoño se vende bien el ganado.
A84: shearer | B84: =IFERROR(INDEX(Personas!$B:$B,MATCH(A84,Personas!$A:$A,0)),"(¿quién?)") | C84: invierno | D84: En invierno casi no salgo, pero hoy hacía falta.
A85: gilbert | B85: =IFERROR(INDEX(Personas!$B:$B,MATCH(A85,Personas!$A:$A,0)),"(¿quién?)") | C85: dice | D85: ¡Buenos días, Zanahorias!... Perdón, perdón. Era una broma, Ana. | F85: zanahorias
A86: gilbert | B86: =IFERROR(INDEX(Personas!$B:$B,MATCH(A86,Personas!$A:$A,0)),"(¿quién?)") | C86: dice | D86: ¿Me vas a hablar algún día, Ana Shirley? | F86: zanahorias
A87: gilbert | B87: =IFERROR(INDEX(Personas!$B:$B,MATCH(A87,Personas!$A:$A,0)),"(¿quién?)") | C87: dice | D87: Te gané en ortografía. Pero en composición... bueno, ahí ganas tú. | F87: escuela | G87: 3
A88: gilbert | B88: =IFERROR(INDEX(Personas!$B:$B,MATCH(A88,Personas!$A:$A,0)),"(¿quién?)") | C88: dice | D88: ¿Quieres que te ayude a cruzar el arroyo? ¿No? Bueno... | E88: sí
A89: gilbert | B89: =IFERROR(INDEX(Personas!$B:$B,MATCH(A89,Personas!$A:$A,0)),"(¿quién?)") | C89: ana | D89: Hmpf. | F89: zanahorias
A90: gilbert | B90: =IFERROR(INDEX(Personas!$B:$B,MATCH(A90,Personas!$A:$A,0)),"(¿quién?)") | C90: ana | D90: No le hablo a Gilbert Blythe. Nunca jamás. | F90: zanahorias
A91: gilbert | B91: =IFERROR(INDEX(Personas!$B:$B,MATCH(A91,Personas!$A:$A,0)),"(¿quién?)") | C91: ana | D91: (Ana sigue de largo con la nariz en alto.) | F91: zanahorias
A92: buhonero | B92: =IFERROR(INDEX(Personas!$B:$B,MATCH(A92,Personas!$A:$A,0)),"(¿quién?)") | C92: dice | D92: ¡Cintas, botones, peinetas, tinte para el pelo! ¡Todo lo que una señorita necesita!
A93: buhonero | B93: =IFERROR(INDEX(Personas!$B:$B,MATCH(A93,Personas!$A:$A,0)),"(¿quién?)") | C93: dice | D93: Un tinte que deja el pelo negro azabache, señorita. Garantizado.
A94: josie | B94: =IFERROR(INDEX(Personas!$B:$B,MATCH(A94,Personas!$A:$A,0)),"(¿quién?)") | C94: dice | D94: ¿Ese vestido es nuevo, Ana? Ah, no... es el de siempre.
A95: josie | B95: =IFERROR(INDEX(Personas!$B:$B,MATCH(A95,Personas!$A:$A,0)),"(¿quién?)") | C95: dice | D95: Te apuesto a que no te atreves a caminar por el techo de la casa de los Barry.
A96: josie | B96: =IFERROR(INDEX(Personas!$B:$B,MATCH(A96,Personas!$A:$A,0)),"(¿quién?)") | C96: dice | D96: Mi mamá dice que las pelirrojas tienen mal genio. ¿Es verdad?
A97: josie | B97: =IFERROR(INDEX(Personas!$B:$B,MATCH(A97,Personas!$A:$A,0)),"(¿quién?)") | C97: ana | D97: Josie Pye, eres... ¡eres una Pye!
A98: josie | B98: =IFERROR(INDEX(Personas!$B:$B,MATCH(A98,Personas!$A:$A,0)),"(¿quién?)") | C98: ana | D98: No pienso contestarte eso.
A99: gertie | B99: =IFERROR(INDEX(Personas!$B:$B,MATCH(A99,Personas!$A:$A,0)),"(¿quién?)") | C99: dice | D99: Josie dice que tú hablas como un libro. ¿Es verdad? Di algo difícil. | E99: sí | J99: !dias_desde:escuela:3
A100: gertie | B100: =IFERROR(INDEX(Personas!$B:$B,MATCH(A100,Personas!$A:$A,0)),"(¿quién?)") | C100: dice | D100: Josie dice que tú inventas palabras difíciles para lucirte. | F100: escuela | G100: 3
...

Sheet Modelo
A1: Clase | B1: Regla | C1: Quién | D1: Tiene | E1: Una situación | F1: Lo que falta

Sheet Cobertura
A1: Prioridad | B1: Área | C1: Qué | D1: Falta | E1: Idea
A2: alta | B2: Situaciones | C2: Ana en camisón en la tienda de Lawson | D2: nadie reacciona, en ningún momento (estaban: el Sr. Lawson, la Sra. Pye) | E2: una escena con «si: ana:camison» (o la hora), y «ve:quien» o «en: quien=tl»
A3: alta | B3: Situaciones | C3: Ana en camisón en la escuela | D3: nadie reacciona, en ningún momento (estaban: el Sr. Phillips, la Srta. Stacy) | E3: una escena con «si: ana:camison» (o la hora), y «ve:quien» o «en: quien=es»
A4: alta | B4: Noticias | C4: «ana_lengua»: la niña de los Cuthbert tiene una lengua, pero buen corazón | D4: nadie reacciona a ella (solo se cuenta) | E4: una escena o una frase con «sabe:quien:ana_lengua» (alguien que se entera y hace o dice algo)
A5: alta | B5: Noticias | C5: «ana_ofendio_lynde»: la niña de los Cuthbert le dijo vieja chismosa a la Sra. Lynde | D5: nadie reacciona a ella (solo se cuenta) | E5: una escena o una frase con «sabe:quien:ana_ofendio_lynde» (alguien que se entera y hace o dice algo)
A6: media | B6: Situaciones | C6: Ana en camisón en La Cuesta del Huerto | D6: nadie reacciona, en ningún momento (estaban: Mary Joe, el Sr. Barry, la Sra. Barry) | E6: una escena con «si: ana:camison» (o la hora), y «ve:quien» o «en: quien=os»
A7: media | B7: Situaciones | C7: Ana en camisón en la casa del Sr. Harrison | D7: nadie reacciona, en ningún momento (estaban: el Sr. Harrison) | E7: una escena con «si: ana:camison» (o la hora), y «ve:quien» o «en: quien=hh»
A8: media | B8: Situaciones | C8: Ana en camisón en la casa parroquial | D8: nadie reacciona, en ningún momento (estaban: el reverendo Allan, la Sra. Allan) | E8: una escena con «si: ana:camison» (o la hora), y «ve:quien» o «en: quien=cp»
A9: media | B9: Situaciones | C9: Ana sin sombrero en Tejas Verdes | D9: nadie reacciona, en ningún momento (estaban: Marilla, Matthew, la Sra. Lynde) | E9: una escena con «si: ana:sin_sombrero» (o la hora), y «ve:quien» o «en: quien=gg»
A10: media | B10: Situaciones | C10: Ana sin sombrero en La Cuesta del Huerto | D10: nadie reacciona, en ningún momento (estaban: Mary Joe, el Sr. Barry, la Sra. Barry) | E10: una escena con «si: ana:sin_sombrero» (o la hora), y «ve:quien» o «en: quien=os»
A11: media | B11: Situaciones | C11: Ana sin sombrero en la Hondonada (Sra. Lynde) | D11: nadie reacciona, en ningún momento (estaban: Thomas Lynde, la Sra. Lynde) | E11: una escena con «si: ana:sin_sombrero» (o la hora), y «ve:quien» o «en: quien=rl»
A12: media | B12: Situaciones | C12: Ana sin sombrero en la casa del Sr. Harrison | D12: nadie reacciona, en ningún momento (estaban: el Sr. Harrison) | E12: una escena con «si: ana:sin_sombrero» (o la hora), y «ve:quien» o «en: quien=hh»
... A109: baja | B109: Hechos | C109: «queens_primera» | D109: se deja y nadie lo lee: algo pasó y no tiene consecuencias | E109: una escena, una frase o una noticia que lo recuerde

Sheet Huecos
A1: Dónde faltan frases: cuántas frases valen de cada uno en cada momento de la historia
A2: «no la conoce»: lo que puede decirle antes de presentarse (sin su nombre); «la conoce»: después. Rojo: ninguna; amarillo: una; verde: dos o más; gris: no está en Avonlea (o, «—», ya la conoce desde el principio). Se calcula con el juego: después de editar las frases, importa y vuelve a generar la planilla para ver los huecos al día.
A4: Quién | B4: Nombre | C4: Día 2 · recién llegada, a prueba | E4: Día 4 · ya se queda | G4: Día 16 · vino la Sra. Lynde | I4: Día 20 · amiga de Diana | K4: Día 33 · va a la escuela | M4: Día 45 · primer invierno | O4: Día 65 · llegan los Allan | Q4: Día 86 · la Srta. Stacy
C5: no la conoce | D5: la conoce | E5: no la conoce | F5: la conoce | G5: no la conoce | H5: la conoce | I5: no la conoce | J5: la conoce | K5: no la conoce | L5: la conoce | M5: no la conoce | N5: la conoce | O5: no la conoce | P5: la conoce | Q5: no la conoce | R5: la conoce
A6: matthew | B6: Matthew | C6: — | D6: 5 | E6: — | F6: 6 | G6: — | H6: 6 | I6: — | J6: 6 | K6: — | L6: 6 | M6: — | N6: 6 | O6: — | P6: 6 | Q6: — | R6: 6
A7: marilla | B7: Marilla | C7: — | D7: 4 | E7: — | F7: 3 | G7: — | H7: 3 | I7: — | J7: 4 | K7: — | L7: 4 | M7: — | N7: 4 | O7: — | P7: 4 | Q7: — | R7: 4
A8: diana | B8: Diana | C8: fuera | D8: fuera | E8: fuera | F8: fuera | G8: fuera | H8: fuera | I8: 5 | J8: 5 | K8: 5 | L8: 6 | M8: 5 | N8: 6 | O8: 4 | P8: 6 | Q8: 5 | R8: 6
A9: barry | B9: la Sra. Barry | C9: 0 | D9: 1 | E9: 0 | F9: 1 | G9: 0 | H9: 1 | I9: 1 | J9: 2 | K9: 2 | L9: 3 | M9: 1 | N9: 2 | O9: 1 | P9: 3 | Q9: 2 | R9: 3
A10: lynde | B10: la Sra. Lynde | C10: 2 | D10: 2 | E10: 2 | F10: 2 | G10: 5 | H10: 6 | I10: 5 | J10: 6 | K10: 5 | L10: 6 | M10: 4 | N10: 5 | O10: 5 | P10: 6 | Q10: 5 | R10: 6
A11: harrison | B11: el Sr. Harrison | C11: 4 | D11: 4 | E11: 4 | F11: 4 | G11: 4 | H11: 4 | I11: 4 | J11: 4 | K11: 4 | L11: 4 | M11: 4 | N11: 4 | O11: 4 | P11: 4 | Q11: 4 | R11: 4
A12: shearer | B12: el Sr. Shearer | C12: 4 | D12: 4 | E12: 4 | F12: 4 | G12: 4 | H12: 4 | I12: 4 | J12: 4 | K12: 4 | L12: 4 | M12: 4 | N12: 4 | O12: 4 | P12: 4 | Q12: 4 | R12: 4
A13: gilbert | B13: Gilbert Blythe | C13: fuera | D13: fuera | E13: fuera | F13: fuera | G13: fuera | H13: fuera | I13: fuera | J13: fuera | K13: 1 | L13: 2 | M13: 1 | N13: 2 | O13: 1 | P13: 2 | Q13: 1 | R13: 2
A14: buhonero | B14: el buhonero | C14: fuera | D14: fuera | E14: 2 | F14: 2 | G14: fuera | H14: fuera | I14: fuera | J14: fuera | K14: fuera | L14: fuera | M14: fuera | N14: fuera | O14: fuera | P14: fuera | Q14: fuera | R14: fuera
A15: josie | B15: Josie Pye | C15: 2 | D15: 3 | E15: 2 | F15: 3 | G15: 2 | H15: 3 | I15: 2 | J15: 3 | K15: 2 | L15: 3 | M15: 2 | N15: 3 | O15: 2 | P15: 3 | Q15: 2 | R15: 3
A16: gertie | B16: Gertie Pye | C16: 0 | D16: 1 | E16: 0 | F16: 1 | G16: 0 | H16: 1 | I16: 0 | J16: 1 | K16: 2 | L16: 2 | M16: 2 | N16: 2 | O16: 2 | P16: 2 | Q16: 2 | R16: 2
A17: ruby | B17: Ruby Gillis | C17: 2 | D17: 3 | E17: 2 | F17: 3 | G17: 2 | H17: 3 | I17: 2 | J17: 3 | K17: 2 | L17: 3 | M17: 2 | N17: 3 | O17: 2 | P17: 3 | Q17: 2 | R17: 3
A18: jane | B18: Jane Andrews | C18: 0 | D18: 1 | E18: 0 | F18: 1 | G18: 0 | H18: 1 | I18: 0 | J18: 1 | K18: 1 | L18: 2 | M18: 1 | N18: 2 | O18: 1 | P18: 2 | Q18: 1 | R18: 2
A19: prissy | B19: Prissy Andrews | C19: 2 | D19: 2 | E19: 2 | F19: 2 | G19: 2 | H19: 2 | I19: 2 | J19: 2 | K19: 2 | L19: 2 | M19: 2 | N19: 2 | O19: 2 | P19: 2 | Q19: fuera | R19: fuera
A20: charlie | B20: Charlie Sloane | C20: 0 | D20: 1 | E20: 0 | F20: 1 | G20: 0 | H20: 1 | I20: 0 | J20: 1 | K20: 0 | L20: 2 | M20: 0 | N20: 2 | O20: 0 | P20: 2 | Q20: 0 | R20: 2
A21: moody | B21: Moody Spurgeon | C21: 2 | D21: 2 | E21: 2 | F21: 2 | G21: 2 | H21: 2 | I21: 2 | J21: 2 | K21: 2 | L21: 2 | M21: 2 | N21: 2 | O21: 2 | P21: 2 | Q21: 2 | R21: 2
A22: tillie | B22: Tillie Boulter | C22: 1 | D22: 1 | E22: 2 | F22: 2 | G22: 2 | H22: 2 | I22: 2 | J22: 2 | K22: 2 | L22: 2 | M22: 2 | N22: 2 | O22: 2 | P22: 2 | Q22: 2 | R22: 2
A23: felicity | B23: Felicity King | C23: 2 | D23: 2 | E23: 2 | F23: 2 | G23: 2 | H23: 2 | I23: 2 | J23: 2 | K23: 2 | L23: 2 | M23: 2 | N23: 2 | O23: 2 | P23: 2 | Q23: 2 | R23: 2
A24: felix | B24: Felix King | C24: 2 | D24: 2 | E24: 2 | F24: 2 | G24: 2 | H24: 2 | I24: 2 | J24: 2 | K24: 2 | L24: 2 | M24: 2 | N24: 2 | O24: 2 | P24: 2 | Q24: 2 | R24: 2
A25: cecily | B25: Cecily King | C25: 0 | D25: 0 | E25: 0 | F25: 0 | G25: 0 | H25: 0 | I25: 0 | J25: 0 | K25: 1 | L25: 1 | M25: 1 | N25: 1 | O25: 1 | P25: 1 | Q25: 1 | R25: 1
A26: sara | B26: Sara Stanley | C26: 1 | D26: 2 | E26: 1 | F26: 2 | G26: 1 | H26: 2 | I26: 1 | J26: 2 | K26: 1 | L26: 2 | M26: 1 | N26: 2 | O26: 1 | P26: 2 | Q26: 1 | R26: 2
A27: phillips | B27: el Sr. Phillips | C27: 1 | D27: 1 | E27: 1 | F27: 1 | G27: 1 | H27: 1 | I27: 1 | J27: 1 | K27: 1 | L27: 2 | M27: 1 | N27: 2 | O27: 1 | P27: 2 | Q27: fuera | R27: fuera
A28: allan | B28: el reverendo Allan | C28: fuera | D28: fuera | E28: fuera | F28: fuera | G28: fuera | H28: fuera | I28: fuera | J28: fuera | K28: fuera | L28: fuera | M28: fuera | N28: fuera | O28: 1 | P28: 2 | Q28: 1 | R28: 2
A29: sraallan | B29: la Sra. Allan | C29: fuera | D29: fuera | E29: fuera | F29: fuera | G29: fuera | H29: fuera | I29: fuera | J29: fuera | K29: fuera | L29: fuera | M29: fuera | N29: fuera | O29: 1 | P29: 3 | Q29: 1 | R29: 3
A30: lawson | B30: el Sr. Lawson | C30: 0 | D30: 1 | E30: 0 | F30: 1 | G30: 0 | H30: 2 | I30: 0 | J30: 2 | K30: 0 | L30: 2 | M30: 0 | N30: 2 | O30: 0 | P30: 2 | Q30: 0 | R30: 2
A31: herrero | B31: el herrero | C31: 2 | D31: 2 | E31: 2 | F31: 2 | G31: 2 | H31: 2 | I31: 2 | J31: 2 | K31: 2 | L31: 2 | M31: 2 | N31: 2 | O31: 2 | P31: 2 | Q31: 2 | R31: 2
A32: editor | B32: el editor de La Crónica | C32: 1 | D32: 2 | E32: 1 | F32: 2 | G32: 1 | H32: 2 | I32: 1 | J32: 2 | K32: 1 | L32: 2 | M32: 1 | N32: 2 | O32: 1 | P32: 2 | Q32: 1 | R32: 2
A33: hetty | B33: la Srta. Hetty King | C33: 2 | D33: 2 | E33: 2 | F33: 2 | G33: 2 | H33: 2 | I33: 2 | J33: 2 | K33: 2 | L33: 2 | M33: 2 | N33: 2 | O33: 2 | P33: 2 | Q33: 2 | R33: 2
A34: olivia | B34: Olivia King | C34: 1 | D34: 2 | E34: 1 | F34: 2 | G34: 1 | H34: 2 | I34: 1 | J34: 2 | K34: 1 | L34: 2 | M34: 1 | N34: 2 | O34: 1 | P34: 2 | Q34: 1 | R34: 2
A35: jasper | B35: Jasper Dale | C35: 2 | D35: 2 | E35: 2 | F35: 2 | G35: 2 | H35: 2 | I35: 2 | J35: 2 | K35: 2 | L35: 2 | M35: 2 | N35: 2 | O35: 2 | P35: 2 | Q35: 2 | R35: 2
A36: alec | B36: Alec King | C36: 1 | D36: 2 | E36: 1 | F36: 2 | G36: 1 | H36: 2 | I36: 1 | J36: 2 | K36: 1 | L36: 2 | M36: 1 | N36: 2 | O36: 1 | P36: 2 | Q36: 1 | R36: 2
A37: janet | B37: Janet King | C37: 2 | D37: 2 | E37: 2 | F37: 2 | G37: 2 | H37: 2 | I37: 2 | J37: 2 | K37: 2 | L37: 2 | M37: 2 | N37: 2 | O37: 2 | P37: 2 | Q37: 2 | R37: 2
A38: srapye | B38: la Sra. Pye | C38: 2 | D38: 2 | E38: 2 | F38: 2 | G38: 2 | H38: 2 | I38: 2 | J38: 2 | K38: 2 | L38: 2 | M38: 2 | N38: 2 | O38: 2 | P38: 2 | Q38: 2 | R38: 2
A39: sloane | B39: el Sr. Sloane | C39: 1 | D39: 1 | E39: 1 | F39: 1 | G39: 1 | H39: 1 | I39: 1 | J39: 1 | K39: 1 | L39: 1 | M39: 1 | N39: 1 | O39: 1 | P39: 1 | Q39: 1 | R39: 1
A40: andrews | B40: el Sr. Andrews | C40: 1 | D40: 1 | E40: 1 | F40: 1 | G40: 1 | H40: 1 | I40: 1 | J40: 1 | K40: 1 | L40: 1 | M40: 1 | N40: 1 | O40: 1 | P40: 1 | Q40: 1 | R40: 1
A41: peg | B41: Peg Bowen | C41: 2 | D41: 2 | E41: 2 | F41: 2 | G41: 2 | H41: 2 | I41: 2 | J41: 2 | K41: 2 | L41: 2 | M41: 2 | N41: 2 | O41: 2 | P41: 2 | Q41: 2 | R41: 2
A42: farero | B42: el capitán Jim | C42: 3 | D42: 3 | E42: 3 | F42: 3 | G42: 3 | H42: 3 | I42: 3 | J42: 3 | K42: 3 | L42: 3 | M42: 3 | N42: 3 | O42: 3 | P42: 3 | Q42: 3 | R42: 3
A43: stacy | B43: la Srta. Stacy | C43: fuera | D43: fuera | E43: fuera | F43: fuera | G43: fuera | H43: fuera | I43: fuera | J43: fuera | K43: fuera | L43: fuera | M43: fuera | N43: fuera | O43: fuera | P43: fuera | Q43: 1 | R43: 3
A44: minnie | B44: Minnie May Barry | C44: 0 | D44: 2 | E44: 0 | F44: 2 | G44: 0 | H44: 2 | I44: 0 | J44: 2 | K44: 0 | L44: 2 | M44: 0 | N44: 2 | O44: 0 | P44: 2 | Q44: 0 | R44: 2
A45: srbarry | B45: el Sr. Barry | C45: 1 | D45: 2 | E45: 1 | F45: 2 | G45: 1 | H45: 2 | I45: 1 | J45: 2 | K45: 1 | L45: 2 | M45: 1 | N45: 2 | O45: 1 | P45: 2 | Q45: 1 | R45: 2
A46: maryjoe | B46: Mary Joe | C46: 1 | D46: 1 | E46: 1 | F46: 1 | G46: 1 | H46: 1 | I46: 1 | J46: 1 | K46: 1 | L46: 1 | M46: 1 | N46: 1 | O46: 1 | P46: 1 | Q46: 1 | R46: 1
A47: jerry | B47: Jerry Buote | C47: 2 | D47: 2 | E47: 2 | F47: 2 | G47: 2 | H47: 2 | I47: 2 | J47: 2 | K47: 2 | L47: 2 | M47: 2 | N47: 2 | O47: 2 | P47: 2 | Q47: 2 | R47: 2
A48: medico | B48: el médico | C48: 1 | D48: 1 | E48: 1 | F48: 1 | G48: 1 | H48: 1 | I48: 1 | J48: 1 | K48: 1 | L48: 1 | M48: 1 | N48: 1 | O48: 1 | P48: 1 | Q48: 1 | R48: 1
A49: srbell | B49: el Sr. Bell | C49: 1 | D49: 1 | E49: 1 | F49: 2 | G49: 1 | H49: 2 | I49: 1 | J49: 2 | K49: 1 | L49: 2 | M49: 1 | N49: 2 | O49: 1 | P49: 2 | Q49: 1 | R49: 2
A50: josephine | B50: la Srta. Josephine Barry | C50: fuera | D50: fuera | E50: fuera | F50: fuera | G50: fuera | H50: fuera | I50: fuera | J50: fuera | K50: fuera | L50: fuera | M50: 0 | N50: 0 | O50: fuera | P50: fuera | Q50: fuera | R50: fuera
A51: spencer | B51: la Sra. Spencer | C51: — | D51: 2 | E51: — | F51: 2 | G51: — | H51: 2 | I51: — | J51: 2 | K51: — | L51: 2 | M51: — | N51: 2 | O51: — | P51: 2 | Q51: — | R51: 2
A52: blewett | B52: la Sra. Blewett | C52: 1 | D52: 1 | E52: 2 | F52: 2 | G52: 2 | H52: 2 | I52: 2 | J52: 2 | K52: 2 | L52: 2 | M52: 2 | N52: 2 | O52: 2 | P52: 2 | Q52: 2 | R52: 2
A53: carrie | B53: Carrie Sloane | C53: 0 | D53: 0 | E53: 0 | F53: 0 | G53: 0 | H53: 0 | I53: 0 | J53: 0 | K53: 0 | L53: 0 | M53: 0 | N53: 0 | O53: 0 | P53: 0 | Q53: 0 | R53: 1
A54: jefe | B54: el jefe de estación | C54: 2 | D54: 2 | E54: 2 | F54: 2 | G54: 2 | H54: 2 | I54: 2 | J54: 2 | K54: 2 | L54: 2 | M54: 2 | N54: 2 | O54: 2 | P54: 2 | Q54: 2 | R54: 2
A55: thomas | B55: Thomas Lynde | C55: 1 | D55: 1 | E55: 1 | F55: 1 | G55: 1 | H55: 1 | I55: 1 | J55: 1 | K55: 1 | L55: 1 | M55: 1 | N55: 1 | O55: 1 | P55: 1 | Q55: 1 | R55: 1
A56: veraneante | B56: una veraneante del hotel | C56: fuera | D56: fuera | E56: fuera | F56: fuera | G56: 2 | H56: 2 | I56: 2 | J56: 2 | K56: fuera | L56: fuera | M56: fuera | N56: fuera | O56: fuera | P56: fuera | Q56: fuera | R56: fuera
A57: pescador | B57: un pescador | C57: 1 | D57: 1 | E57: 1 | F57: 1 | G57: 1 | H57: 1 | I57: 1 | J57: 1 | K57: 1 | L57: 1 | M57: 1 | N57: 1 | O57: 1 | P57: 1 | Q57: 1 | R57: 1
A58: vecino | B58: un vecino (sin nombre) | C58: 5 | D58: 5 | E58: 5 | F58: 5 | G58: 4 | H58: 5 | I58: 4 | J58: 5 | K58: 4 | L58: 5 | M58: 4 | N58: 5 | O58: 4 | P58: 5 | Q58: 4 | R58: 5
A59: niño | B59: un niño (sin nombre) | C59: 2 | D59: 3 | E59: 2 | F59: 3 | G59: 2 | H59: 3 | I59: 2 | J59: 3 | K59: 2 | L59: 3 | M59: 2 | N59: 3 | O59: 2 | P59: 3 | Q59: 2 | R59: 3
A60: adultos | B60: (todos los grandes) | C60: — | D60: — | E60: — | F60: — | G60: — | H60: — | I60: — | J60: — | K60: — | L60: — | M60: — | N60: — | O60: — | P60: — | Q60: — | R60: —
A61: niños | B61: (todos los niños) | C61: — | D61: — | E61: — | F61: — | G61: — | H61: — | I61: — | J61: — | K61: — | L61: — | M61: — | N61: — | O61: — | P61: — | Q61: — | R61: —
B63: Huecos (casillas en 0) | C63: =COUNTIF(C6:C61,0) | D63: =COUNTIF(D6:D61,0) | E63: =COUNTIF(E6:E61,0) | F63: =COUNTIF(F6:F61,0) | G63: =COUNTIF(G6:G61,0) | H63: =COUNTIF(H6:H61,0) | I63: =COUNTIF(I6:I61,0) | J63: =COUNTIF(J6:J61,0) | ... R63: =COUNTIF(R6:R61,0)

Sheet Listas
A1: Quién | B1: Tipo | C1: ¿Conoce a Ana? | D1: Estación | E1: Hechos y metas
A2: matthew | B2: dice | C2: sí | D2: primavera | E2: a_prueba
A3: marilla | B3: ana | C3: no | D3: verano | E3: allan
A4: diana | B4: primavera | D4: otoño | E4: allan_invitados
A5: barry | B5: verano | D5: invierno | E5: amigas
A6: lynde | B6: otoño | E6: ana
A7: harrison | B7: invierno | E7: ana_admite_gilbert
A8: shearer | E8: barry
A9: gilbert | E9: barry_presenta
A10: buhonero | E10: blewett_calla
A11: josie | E11: blewett_duda
A12: gertie | E12: blewett_orgullo
A13: ruby | E13: blewett_suplica
A14: jane | E14: broche
A15: prissy | E15: broche_confeso
A16: charlie | E16: broche_verdad
A17: moody | E17: cama_josephine
A18: tillie | E18: carta
A19: felicity | E19: clase
... A57: niños | E57: historia_llegada
E58: historia_llegada_cerrado
E59: historia_matthew_aliado
E60: historia_matthew_aliado_cerrado
E61: historia_pedir_perdon
E62: historia_pedir_perdon_a_lo_grande
E63: historia_pedir_perdon_cerrado
E64: historia_rival
E65: historia_rival_cerrado
E66: historia_rival_le_contesta
E67: historia_rival_lo_ignora
E68: historia_rival_pizarra
E69: historia_sombrero_iglesia
... E170: {k}

Sheet Personas
A1: Quién (id) | B1: Nombre | C1: Grupo | D1: Vive en | E1: Llega a Avonlea si… | F1: Se va si… | G1: Frases | H1: Quién es
A2: matthew | B2: Matthew | C2: casa | D2: out | G2: =COUNTIF(Frases!$A:$A,A2) | H2: unos sesenta años, hermano de Marilla. Tímidísimo, de muy pocas palabras, le dan miedo casi todas las mujeres, pero adora a Ana y siempre se pone de su lado. Tr
A3: marilla | B3: Marilla | C3: casa | D3: gg | G3: =COUNTIF(Frases!$A:$A,A3) | H3: hermana de Matthew, severa, práctica y ordenada, con un humor seco que esconde; quiere mucho a Ana aunque le cuesta decirlo, y la reprende por soñar despierta o
A4: diana | B4: Diana | C4: casa | D4: out | E4: dias_desde:llegada_tv:17 | G4: =COUNTIF(Frases!$A:$A,A4) | H4: la amiga del alma de Ana, de pelo negro y rizado, dulce, alegre y un poco miedosa; admira la imaginación de Ana. Se juraron amistad eterna. Una vez Ana le sirvi
A5: barry | B5: la Sra. Barry | C5: casa | D5: os | G5: =COUNTIF(Frases!$A:$A,A5) | H5: la madre de Diana. Correcta, estricta y algo estirada; desconfió de Ana después de lo del vino, pero ahora la aprecia, con cierta cautela. No sale de su salita.
A6: lynde | B6: la Sra. Lynde | C6: casa | D6: rl | G6: =COUNTIF(Frases!$A:$A,A6) | H6: la vecina chismosa y mandona de Marilla; gordita, activa y de buen corazón, dice siempre lo que piensa y opina de todo (de la crianza de Ana, del pelo, de la hu
A7: harrison | B7: el Sr. Harrison | C7: casa | D7: hh | G7: =COUNTIF(Frases!$A:$A,A7) | H7: el vecino nuevo de los Cuthbert: bajo, gordo y calvo, con barba rojiza; gruñón, desordenado (su casa es un caos de platos sin lavar y periódicos) y de mal genio
A8: shearer | B8: el Sr. Shearer | C8: casa | D8: away | G8: =COUNTIF(Frases!$A:$A,A8) | H8: un comerciante de ganado de Carmody: práctico, amable y siempre apurado; recorre los caminos con su carreta comprando vacas y terneros, y paga al contado.
A9: gilbert | B9: Gilbert Blythe | C9: niños | D9: Casa de los Blythe | E9: dias_desde:escuela:4 · o · estacion:invierno | G9: =COUNTIF(Frases!$A:$A,A9) | H9: Gilbert Blythe, 13 años, el chico más listo y simpático de la escuela; una vez llamó «Zanahorias» a Ana y ella le rompió la pizarra en la cabeza; desde entonces
A10: buhonero | B10: el buhonero | C10: pueblo | D10: Pensión | E10: (de visita) dia_estacion:4 · o · dia_estacion:11 | G10: =COUNTIF(Frases!$A:$A,A10) | H10: un vendedor ambulante que va de casa en casa con su baúl de cintas, botones y tinte para el pelo (el que le vendió a Ana el tinte que le dejó el pelo verde)
A11: josie | B11: Josie Pye | C11: niños | D11: Casa de los Pye | G11: =COUNTIF(Frases!$A:$A,A11) | H11: Josie Pye, compañera de escuela de Ana, presumida, envidiosa y de lengua afilada; siempre está desafiando a los demás
A12: gertie | B12: Gertie Pye | C12: niños | D12: Casa de los Pye | G12: =COUNTIF(Frases!$A:$A,A12) | H12: Gertie Pye, hermana menor de Josie, imita todo lo que dice su hermana
A13: ruby | B13: Ruby Gillis | C13: niños | D13: Casa de los Gillis | G13: =COUNTIF(Frases!$A:$A,A13) | H13: Ruby Gillis, compañera de Ana, bonita y romántica, siempre hablando de pretendientes
A14: jane | B14: Jane Andrews | C14: niños | D14: Granja Andrews | G14: =COUNTIF(Frases!$A:$A,A14) | H14: Jane Andrews, compañera de Ana, sensata, trabajadora y sin mucha imaginación
A15: prissy | B15: Prissy Andrews | C15: niños | D15: Granja Andrews | F15: hecho:se_fue_phillips | G15: =COUNTIF(Frases!$A:$A,A15) | H15: Prissy Andrews, 16 años, la mayor de la escuela, se da aires de señorita y estudia para entrar a Queen's
A16: charlie | B16: Charlie Sloane | C16: niños | D16: Granja Sloane | G16: =COUNTIF(Frases!$A:$A,A16) | H16: Charlie Sloane, compañero de escuela de Ana, tímido, de ojos saltones, enamorado de Ana
A17: moody | B17: Moody Spurgeon | C17: niños | D17: Pensión | G17: =COUNTIF(Frases!$A:$A,A17) | H17: Moody Spurgeon MacPherson, compañero de escuela de Ana, serio y torpe, quiere ser pastor
A18: tillie | B18: Tillie Boulter | C18: niños | D18: Casa de los Potts | G18: =COUNTIF(Frases!$A:$A,A18) | H18: Tillie Boulter, compañera de escuela de Ana, alegre y juguetona
A19: felicity | B19: Felicity King | C19: niños | D19: Granja King | G19: =COUNTIF(Frases!$A:$A,A19) | H19: Felicity King, de la granja King, muy hacendosa y orgullosa de su cocina
A20: felix | B20: Felix King | C20: niños | D20: Granja King | G20: =COUNTIF(Frases!$A:$A,A20) | H20: Felix King, de la granja King, regordete, crédulo y fanfarrón
A21: cecily | B21: Cecily King | C21: niños | D21: Granja King | G21: =COUNTIF(Frases!$A:$A,A21) | H21: Cecily King, de la granja King, la más pequeña, dulce y tímida
A22: sara | B22: Sara Stanley | C22: niños | D22: Rose Cottage | G22: =COUNTIF(Frases!$A:$A,A22) | H22: Sara Stanley, la niña de la historia, que vive en Rose Cottage con sus tías; cuenta historias maravillosas
A23: phillips | B23: el Sr. Phillips | C23: pueblo | D23: Pensión | F23: estacion:verano, hecho:llego_josephine | G23: =COUNTIF(Frases!$A:$A,A23) | H23: el Sr. Phillips, el maestro de Avonlea, severo y algo distraído, que corteja a Prissy Andrews
A24: allan | B24: el reverendo Allan | C24: pueblo | D24: Casa parroquial | E24: estacion:primavera, dias_desde:se_fue_josephine:7 | G24: =COUNTIF(Frases!$A:$A,A24) | H24: el reverendo Allan, el nuevo pastor de Avonlea, joven, bondadoso y de buen humor
A25: sraallan | B25: la Sra. Allan | C25: pueblo | D25: Casa parroquial | E25: estacion:primavera, dias_desde:se_fue_josephine:7 | G25: =COUNTIF(Frases!$A:$A,A25) | H25: la Sra. Allan, esposa del pastor, joven, dulce y alegre; Ana la adora (es su «espíritu afín»)
A26: lawson | B26: el Sr. Lawson | C26: pueblo | D26: Tienda de Lawson | G26: =COUNTIF(Frases!$A:$A,A26) | H26: el Sr. Lawson, dueño de la tienda de la aldea, amable y conversador
A27: herrero | B27: el herrero | C27: pueblo | D27: Herrería | G27: =COUNTIF(Frases!$A:$A,A27) | H27: el herrero de Avonlea, grandote, tiznado y de buen corazón
A28: editor | B28: el editor de La Crónica | C28: pueblo | D28: La Crónica de Avonlea | G28: =COUNTIF(Frases!$A:$A,A28) | H28: el editor de La Crónica de Avonlea, el periódico del pueblo, siempre buscando noticias
A29: hetty | B29: la Srta. Hetty King | C29: pueblo | D29: Rose Cottage | G29: =COUNTIF(Frases!$A:$A,A29) | H29: la Srta. Hetty King, de Rose Cottage, solterona estricta y orgullosa, con mucho corazón escondido
A30: olivia | B30: Olivia King | C30: pueblo | D30: Rose Cottage | G30: =COUNTIF(Frases!$A:$A,A30) | H30: Olivia King, hermana de Hetty, dulce y romántica, a quien corteja Jasper Dale
A31: jasper | B31: Jasper Dale | C31: pueblo | D31: Casa de Jasper | G31: =COUNTIF(Frases!$A:$A,A31) | H31: Jasper Dale, el inventor tímido de Avonlea, que tartamudea y se sonroja; enamorado de Olivia King
A32: alec | B32: Alec King | C32: pueblo | D32: Granja King | G32: =COUNTIF(Frases!$A:$A,A32) | H32: Alec King, granjero, hermano de Hetty, trabajador y de pocas palabras
A33: janet | B33: Janet King | C33: pueblo | D33: Granja King | G33: =COUNTIF(Frases!$A:$A,A33) | H33: Janet King, esposa de Alec, madre práctica y cariñosa
A34: srapye | B34: la Sra. Pye | C34: pueblo | D34: Casa de los Pye | G34: =COUNTIF(Frases!$A:$A,A34) | H34: la Sra. Pye, madre de Josie y Gertie, chismosa y criticona
A35: sloane | B35: el Sr. Sloane | C35: pueblo | D35: Granja Sloane | G35: =COUNTIF(Frases!$A:$A,A35) | H35: el Sr. Sloane, granjero, padre de Charlie
A36: andrews | B36: el Sr. Andrews | C36: pueblo | D36: Granja Andrews | G36: =COUNTIF(Frases!$A:$A,A36) | H36: el Sr. Andrews, granjero, padre de Jane y Prissy, serio y formal
A37: peg | B37: Peg Bowen | C37: pueblo | D37: Casa de Peg Bowen | G37: =COUNTIF(Frases!$A:$A,A37) | H37: Peg Bowen, la vieja excéntrica que vive sola en el bosque; los niños creen que es bruja, pero es buena y sabia a su manera
A38: farero | B38: el capitán Jim | C38: pueblo | D38: Casa del farero | G38: =COUNTIF(Frases!$A:$A,A38) | H38: el capitán Jim, el viejo farero, marinero retirado que cuenta historias del mar
A39: stacy | B39: la Srta. Stacy | C39: pueblo | D39: Pensión | E39: estacion:otoño, hecho:se_fue_phillips | G39: =COUNTIF(Frases!$A:$A,A39) | H39: la Srta. Stacy, la maestra nueva de Avonlea: joven, alegre y comprensiva; saca a los alumnos a estudiar al bosque y prepara a los mejores para el examen de Quee
A40: minnie | B40: Minnie May Barry | C40: pueblo | D40: La Cuesta del Huerto | G40: =COUNTIF(Frases!$A:$A,A40) | H40: Minnie May Barry, la hermanita de Diana, de tres años; Ana la salvó del crup una noche de invierno
A41: srbarry | B41: el Sr. Barry | C41: pueblo | D41: La Cuesta del Huerto | G41: =COUNTIF(Frases!$A:$A,A41) | H41: el Sr. Barry, el padre de Diana, granjero de La Cuesta del Huerto, callado y trabajador
A42: maryjoe | B42: Mary Joe | C42: pueblo | D42: La Cuesta del Huerto | G42: =COUNTIF(Frases!$A:$A,A42) | H42: Mary Joe, la muchacha francesa que trabaja en casa de los Barry; no sabe qué hacer en una emergencia
A43: jerry | B43: Jerry Buote | C43: pueblo | D43: Tejas Verdes | G43: =COUNTIF(Frases!$A:$A,A43) | H43: Jerry Buote, el muchacho francés que Matthew contrata para ayudar en la granja de Tejas Verdes
A44: medico | B44: el médico | C44: pueblo | D44: Pensión | G44: =COUNTIF(Frases!$A:$A,A44) | H44: el médico de la zona, que atiende a los enfermos de Avonlea; un señor serio y amable
A45: srbell | B45: el Sr. Bell | C45: pueblo | D45: Casa de los Pettibone | G45: =COUNTIF(Frases!$A:$A,A45) | H45: el Sr. Bell, el superintendente de la escuela dominical, un señor mayor y muy formal que hace oraciones larguísimas
A46: josephine | B46: la Srta. Josephine Barry | C46: pueblo | D46: La Cuesta del Huerto | E46: (de visita) estacion:invierno | G46: =COUNTIF(Frases!$A:$A,A46) | H46: la Srta. Josephine Barry, la tía rica de Diana, de Charlottetown: brusca y estirada, pero Ana la hace reír como nadie; de visita en La Cuesta del Huerto
A47: spencer | B47: la Sra. Spencer | C47: pueblo | D47: Hotel White Sands | G47: =COUNTIF(Frases!$A:$A,A47) | H47: la Sra. Spencer, de White Sands, la que trajo a Ana del orfanato por error (los Cuthbert querían un niño)
A48: blewett | B48: la Sra. Blewett | C48: pueblo | D48: Hotel White Sands | G48: =COUNTIF(Frases!$A:$A,A48) | H48: la Sra. Peter Blewett, de White Sands, una mujer dura y tacaña que quería a Ana de sirvienta; Marilla no se la dio
A49: carrie | B49: Carrie Sloane | C49: niños | D49: Granja Sloane | G49: =COUNTIF(Frases!$A:$A,A49) | H49: Carrie Sloane, compañera de escuela de Ana, hermana de Charlie
A50: jefe | B50: el jefe de estación | C50: pueblo | D50: Hotel White Sands | G50: =COUNTIF(Frases!$A:$A,A50) | H50: el jefe de estación, de Avonlea, que vive en Hotel White Sands
A51: thomas | B51: Thomas Lynde | C51: pueblo | D51: La Hondonada de Lynde | G51: =COUNTIF(Frases!$A:$A,A51) | H51: Thomas Lynde, el marido de la Sra. Rachel Lynde, un hombre tranquilo y callado (ella habla por los dos)
A52: veraneante | B52: una veraneante del hotel | C52: pueblo | D52: Hotel White Sands | E52: (de visita) estacion:verano | G52: =COUNTIF(Frases!$A:$A,A52) | H52: una señora de Boston que veranea en el hotel White Sands, encantada con todo
A53: pescador | B53: un pescador | C53: pueblo | D53: Casa del farero | G53: =COUNTIF(Frases!$A:$A,A53) | H53: un pescador de Avonlea, curtido y bromista
A54: vecino | B54: un vecino (sin nombre) | C54: vecinos | G54: =COUNTIF(Frases!$A:$A,A54) | H54: los vecinos del pueblo que no tienen nombre
A55: niño | B55: un niño (sin nombre) | C55: vecinos | G55: =COUNTIF(Frases!$A:$A,A55) | H55: los niños del pueblo que no tienen nombre
A56: adultos | B56: (todos los grandes) | C56: grupos | G56: =COUNTIF(Frases!$A:$A,A56) | H56: lo que dice cualquier grande, además de lo suyo
A57: niños | B57: (todos los niños) | C57: grupos | G57: =COUNTIF(Frases!$A:$A,A57) | H57: lo que dice cualquier niño, además de lo suyo

Sheet Escenas
A1: Escena | B1: Canal | C1: Cómo empieza | D1: Prioridad | E1: Interrumpe | F1: Grande | G1: Se repite | H1: Si… (condiciones, con comas) | I1: Dónde está cada uno (en) | J1: Quedan quietos | K1: Narra (el cartel) | L1: Al empezar (una acción por línea) | M1: Al terminar (una acción por línea) | N1: Otros campos (uno por línea) | O1: Hablan | P1: Líneas | Q1: Empieza con
A2: rachel_ventana | B2: rl | D2: 6 | H2: capitulo, marca:rachel_ve | I2: lynde=rl | K2: Avonlea, un pueblito de granjas en la Isla del Príncipe Eduardo, en Canadá, a fines del siglo XIX. Una tarde de comienzos de junio. La Sra. Rachel Lynde vive donde el camino baja a la hondonada, y desde su ventana no se le escapa nada de lo que pasa en Avonlea. Y hoy ve algo rarísimo: Matthew Cuthbert, el hombre más tímido del pueblo, sale en la calesa, de cuello blanco y su mejor traje. | O2: lynde | P2: 3 | Q2: narra: Avonlea, un pueblito de granjas en la Isla del Príncipe Eduardo, en Canadá, a fines del siglo XIX. Una tarde de comienzos de junio.
A3: mesa_tres | B3: gg | D3: 4 | H3: capitulo, marca:mesa_tres | I3: marilla=gg | O3: marilla | P3: 1 | Q3: marilla: Tres platos. Matthew, yo… y el niño.
A4: rachel_marilla | B4: gg | D4: 9 | E4: sí | H4: capitulo, hecho:rachel_llego_tejas_verdes | I4: lynde=gg, marilla=gg | J4: lynde, marilla | L4: marca marilla_cuenta | Marilla le contó a Rachel que Matthew fue a Bright River a buscar a un niño huérfano de Nueva Escocia. | M4: hecho rachel_lo_sabe saber lynde huerfano meta lynde estar_en casa_bell,-,- | Rachel va a casa de los Bell a contar la noticia | ir a casa de Robert Bell a contar la noticia (cap. 1) | 3 | N4: lineas: libro:rachel_marilla | P4: 28 | Q4: marilla: Buenas tardes, Rachel. Qué tarde tan linda, ¿no? Siéntate. ¿Cómo están todos en tu casa?
A5: rachel_bell | B5: bell | D5: 9 | H5: capitulo, hecho:rachel_en_casa_bell | J5: lynde | M5: soltar srbell meta lynde estar_en h:rl,-,21.5 | Rachel vuelve a su casa, a la ventana | volver a casa, tomar el té y vigilar el camino desde la ventana (cap. 1) | N5: cerca: lynde, casa_bell, 160 lineas: libro:rachel_bell | P5: 6 | Q5: lynde: ¡Robert, señora Bell, no van a creer lo que les vengo a contar! Siéntense, que es para caerse de espaldas, eso es lo que es.
A6: estacion | B6: br | D6: 9 | H6: capitulo, hecho:matthew_en_estacion, ana_visible, escena_ana:br | I6: matthew=br | J6: matthew | K6: En la estación de Bright River, a ocho millas de Avonlea. Matthew viene a buscar al niño del orfanato que la Sra. Spencer quedó en traer. Pero en el andén no hay ningún niño. | L6: marca jefe_explica | El jefe de estación le explicó a Matthew que solo había llegado una niña; Matthew decidió llevarla a casa y que Marilla aclarara el error. | M6: ana sit=false meta matthew llevar ana,cocina | | llevar a la niña a Tejas Verdes en la calesa (cap. 2) | 3 | N6: lineas: libro:estacion marcas: 8=matthew_nina | P6: 25 | Q6: narra: En la estación de Bright River, a ocho millas de Avonlea. Matthew viene a buscar al niño del orfanato que la Sra. Spencer quedó en traer. Pero en el andén no hay ningún niño.
A7: avenida | B7: viaje | D7: 10 | E7: sí | N7: calesa: camino camino: tramo=avenida lineas: libro:viaje.10 [7] | O7: matthew | P7: 4 | Q7: ana: Lo que es seguro es que nunca seré angelicalmente buena. La señora Spencer dice… ¡oh, señor Cuthbert! ¡Oh, señor Cuthbert!! ¡Oh, señor Cuthbert!!!
A8: newbridge | B8: viaje | D8: 8 | E8: sí | H8: dicha:avenida | N8: calesa: camino camino: tramo=Newbridge | P8: 1 | Q8: ana: (Callada todavía. Los perros les ladran, los chicos gritan desde las cercas, hay caras curiosas en las ventanas: Ana no ve nada de eso.)
A9: avenida_petalos | B9: viaje | D9: 1.5 | H9: dicha:avenida | N9: pausa: 12 calesa: camino camino: tramo=avenida | P9: 1 | Q9: ana: (Ana echa la cabeza atrás para mirar la bóveda de flores. Los pétalos le caen en el pelo y no se los quita.)
A10: avenida_paso | B10: viaje | D10: 1.5 | H10: dicha:avenida_petalos | N10: pausa: 12 calesa: camino camino: tramo=avenida | O10: matthew | P10: 1 | Q10: matthew: (Matthew afloja las riendas. La yegua va al paso, como si también ella quisiera que esto no se acabara.)
A11: avenida_roseton | B11: viaje | D11: 1.5 | H11: dicha:avenida_paso | N11: pausa: 12 calesa: camino camino: tramo=avenida | P11: 1 | Q11: ana: (Al fondo de la Avenida, el cielo del atardecer brilla como el rosetón de una catedral.)
A12: newbridge_ventanas | B12: viaje | D12: 1.5 | H12: dicha:newbridge | N12: pausa: 12 calesa: camino camino: tramo=Newbridge | P12: 1 | Q12: ana: (Las ventanas del pueblo se encienden una a una. Ana sigue mirando hacia atrás, hacia donde quedó la Avenida.)
A13: silencio_manos | B13: viaje | D13: 1.5 | H13: dicha:avenida | N13: pausa: 14 calesa: camino camino: tramo=campos | P13: 1 | Q13: ana: (Ana va callada, con las manos juntas sobre el bolso de alfombra y los ojos en el cielo del oeste.)
A14: silencio_matthew | B14: viaje | D14: 1.5 | H14: dicha:silencio_manos | N14: pausa: 14 calesa: camino camino: tramo=campos | O14: matthew | P14: 1 | Q14: matthew: (Matthew la mira de reojo. Nunca pensó que el silencio de una niña pudiera ser tan cómodo.)
A15: silencio_estrella | B15: viaje | D15: 1.5 | H15: dicha:silencio_matthew | N15: pausa: 14 calesa: camino camino: tramo=campos | P15: 1 | Q15: ana: (Sobre los campos aparece la primera estrella. Ana mueve los labios: quizás le está pidiendo un deseo.)
A16: silencio_ranas | B16: viaje | D16: 1.5 | H16: dicha:silencio_estrella | N16: pausa: 14 calesa: camino camino: tramo=campos | O16: matthew | P16: 1 | Q16: matthew: (En una laguna junto al camino empiezan a cantar las ranas. La yegua resopla: ya huele su casa.)
A17: silencio_nombre | B17: viaje | D17: 1.5 | H17: dicha:silencio_ranas | N17: pausa: 14 calesa: camino camino: tramo=campos | P17: 1 | Q17: ana: ~Blanco… de las Delicias… no, todavía no…
A18: nombra_avenida | B18: viaje | D18: 9 | E18: sí | H18: dicha:avenida | L18: log Matthew rompió el silencio: «solo nos falta una milla». | N18: o: calesa=camino camino.desde=.955 o: calesa=avonlea cerca=matthew,letrero_br,2500 lineas: libro:avonlea.camino_blanco [1,2,3,4] marcas: 0=una_milla | P18: 7 | Q18: matthew: (después de Newbridge y tres millas de silencio) Supongo que estarás bien cansada y con hambre. Pero ya no falta mucho: solo una milla más.
A19: lago | B19: viaje | D19: 9 | E19: sí | L19: log Matthew le mostró la laguna de Barry. | N19: calesa: avonlea cerca: matthew, lago, 1300 lineas: libro:avonlea.lago [0] marcas: 0=lago | O19: matthew | P19: 6 | Q19: matthew: Ésa es la laguna de Barry.
A20: tejas_verdes | B20: viaje | D20: 9 | E20: sí | H20: dicha:lago | L20: log Ana adivinó cuál era Tejas Verdes, bajo una gran estrella blanca. | N20: o: calesa=avonlea cerca=matthew,tejas_verdes,1700 si=y_mayor:matthew:61 o: si=capitulo,hecho:matthew_llego_casa,!hecho:llegaron lineas: libro:avonlea.tejas_verdes [0,1,2,3,4,8,9] marcas: 2=adivina_tv | P20: 7 | Q20: matthew: Ya estamos bien cerca de casa. Ésa de allá es Tejas Verdes…
A21: llegada | B21: gg | D21: 10 | H21: capitulo, hecho:llegaron, canal_libre:viaje, escena_ana:gg | I21: marilla=gg | J21: matthew, marilla | L21: log Marilla vio a la niña de pelo rojo: «Matthew Cuthbert, ¿quién es ésa? ¿Dónde está el niño?» | M21: fin_capitulo hecho llegada_tv | N21: lineas: libro:llegada marcas: 0=marilla_nino | P21: 7 | Q21: marilla: Matthew Cuthbert, ¿quién es ésa? ¿Dónde está el niño?
A22: relleno | B22: viaje | D22: 0 | G22: cada 30 | N22: tipo: comentario calesa: camino camino: no_callado lineas: relleno:1 | P22: 1 | Q22: ana: Esa cerca en zigzag parece una costura hecha por un gigante muy distraído.
A23: carta_diana_1 | B23: carta | D23: 5 | H23: carta:diana | N23: entre: 5 | P23: 13 | Q23: ana: (Ana moja la pluma en el tintero y se queda mirando el papel en blanco.)
A24: carta_diana_2 | B24: carta | D24: 5 | G24: siempre | H24: carta:diana, dicha:carta_diana_1 | N24: entre: 5 | P24: 11 | Q24: ana: (Ana estira el papel con la palma de la mano, muy seria.)
A25: carta_stacy_1 | B25: carta | D25: 5 | H25: carta:stacy | N25: entre: 5 | P25: 11 | Q25: ana: (Ana se sienta derechita, como en la escuela, y moja la pluma.)
A26: carta_stacy_2 | B26: carta | D26: 5 | G26: siempre | H26: carta:stacy, dicha:carta_stacy_1 | N26: entre: 5 | P26: 9 | Q26: ana: (Ana mira el techo, buscando las palabras entre las vigas.)
A27: carta_sraallan_1 | B27: carta | D27: 5 | H27: carta:sraallan | N27: entre: 5 | P27: 9 | Q27: ana: (Ana busca su mejor papel, el que tiene un borde de florcitas.)
A28: carta_sraallan_2 | B28: carta | D28: 5 | G28: siempre | H28: carta:sraallan, dicha:carta_sraallan_1 | N28: entre: 5 | P28: 7 | Q28: ana: (Ana escribe despacio, con su mejor letra.)
A29: carta_josephine_1 | B29: carta | D29: 5 | H29: carta:josephine | N29: entre: 5 | P29: 8 | Q29: ana: (Ana sopla la pluma antes de empezar, como si fuera a tocar una flauta.)
A30: carta_josephine_2 | B30: carta | D30: 5 | G30: siempre | H30: carta:josephine, dicha:carta_josephine_1 | N30: entre: 5 | P30: 6 | Q30: ana: (Ana se arregla el pelo antes de escribir, como si la tía Josephine pudiera verla.)
A31: carta_spencer_prueba | B31: carta | D31: 5 | H31: carta:spencer, !hecho:se_queda | N31: entre: 5 | P31: 9 | Q31: ana: (Ana moja la pluma y se queda quieta un rato largo. Le tiembla un poco la mano.)
A32: carta_spencer_1 | B32: carta | D32: 5 | G32: siempre | H32: carta:spencer, hecho:se_queda | N32: entre: 5 | P32: 8 | Q32: ana: (Ana escribe con su mejor letra, como si la Sra. Spencer fuera a corregirla.)
A33: resp_diana_1 | B33: respuesta | H33: respuesta:diana | N33: de: diana | P33: 4 | Q33: carta: Querida Ana:
A34: resp_diana_2 | B34: respuesta | H34: respuesta:diana | N34: de: diana | P34: 4 | Q34: carta: Queridísima Ana:
A35: resp_stacy_1 | B35: respuesta | H35: respuesta:stacy | N35: de: stacy | P35: 4 | Q35: carta: Querida Ana:
A36: resp_stacy_2 | B36: respuesta | H36: respuesta:stacy | N36: de: stacy | P36: 4 | Q36: carta: Querida Ana:
A37: resp_sraallan_1 | B37: respuesta | H37: respuesta:sraallan | N37: de: sraallan | P37: 4 | Q37: carta: Querida Ana:
A38: resp_josephine_1 | B38: respuesta | H38: respuesta:josephine | N38: de: josephine | P38: 4 | Q38: carta: Querida Ana:
A39: resp_josephine_2 | B39: respuesta | H39: respuesta:josephine | N39: de: josephine | P39: 4 | Q39: carta: Mi querida Ana:
A40: resp_spencer_prueba | B40: respuesta | H40: respuesta:spencer, !hecho:se_queda | N40: de: spencer responde: carta_spencer_prueba | P40: 4 | Q40: carta: Querida Ana:
A41: resp_spencer_prueba_quedo | B41: respuesta | H41: respuesta:spencer, hecho:se_queda | N41: de: spencer responde: carta_spencer_prueba | P41: 4 | Q41: carta: Querida Ana:
A42: resp_spencer_conocidas_diana | B42: respuesta | H42: respuesta:spencer, hecho:se_queda, hecho:conocidas_diana | N42: de: spencer | P42: 4 | Q42: carta: Querida Ana:
A43: resp_spencer_zanahorias_pizarra | B43: respuesta | H43: respuesta:spencer, hecho:se_queda, hecho:zanahorias_pizarra | N43: de: spencer | P43: 4 | Q43: carta: Querida Ana:
A44: resp_spencer_zanahorias_contesta | B44: respuesta | H44: respuesta:spencer, hecho:se_queda, hecho:zanahorias_contesta | N44: de: spencer | P44: 4 | Q44: carta: Querida Ana:
... A49: resp_spencer_1 | B49: respuesta | H49: respuesta:spencer, hecho:se_queda | N49: de: spencer | P49: 4 | Q49: carta: Querida Ana:
A50: quiere_amiga | B50: gg | D50: 7 | E50: sí | H50: hecho:pide_amiga, !hecho:quiere_amiga, !hecho:conocidas_diana | I50: ana=gg, marilla=gg | J50: marilla | K50: Ana nunca ha tenido una amiga de verdad. En el orfanato y en las casas donde vivió, sus únicas amigas fueron imaginarias: Katie Maurice, la niña que vivía detrás del vidrio de una vitrina, y Violetta, el eco de un valle. | M50: hecho quiere_amiga log Ana le contó a Marilla que quería una amiga del alma, y Marilla le habló de Diana Barry. | yo: le conté a Marilla que quería una amiga del alma, y ella me habló de Diana Barry, la niña de La Cuesta del Huerto. | O50: marilla | P50: 8 | Q50: narra: Ana nunca ha tenido una amiga de verdad. En el orfanato y en las casas donde vivió, sus únicas amigas fueron imaginarias: Katie Maurice, la niña que vivía detrás del vidrio de una vitrina, y Violetta, el eco de un valle.
A51: aviso_barry | B51: gg | D51: 5 | G51: dia | H51: dias_desde:quiere_amiga:1, !hecho:conocidas_diana, !hecho:barry_presenta, presente:diana, hora:6-13 | I51: ana=gg, marilla=gg | J51: marilla | O51: marilla | P51: 2 | Q51: marilla: Ana, esta tarde, después del almuerzo, voy a La Cuesta del Huerto a devolverle un patrón a la Sra. Barry. Si quieres conocer a Diana, no te vayas lejos.
A52: barry_recibe | B52: os | D52: 7 | E52: sí | H52: hecho:quiere_amiga, !hecho:conocidas_diana, !hecho:barry_presenta | I52: ana=os, marilla=os | J52: marilla, barry | K52: La Cuesta del Huerto es la granja de los Barry, al otro lado del arroyo, frente a Tejas Verdes. Allí vive Diana, de la edad de Ana, con sus padres y su hermanita Minnie May. La Sra. Barry es una señora muy estricta. | L52: contar barry nina_cuthbert | M52: hecho barry_presenta meta diana estar_en h:os,-,- | Diana entra a conocer a la niña de Tejas Verdes | entrar a conocer a la niña de Tejas Verdes (cap. 12) | 3 | O52: barry, marilla | P52: 5 | Q52: narra: La Cuesta del Huerto es la granja de los Barry, al otro lado del arroyo, frente a Tejas Verdes. Allí vive Diana, de la edad de Ana, con sus padres y su hermanita Minnie May. La Sra. Barry es una señora muy estricta.
A53: conoce_diana | B53: os | D53: 8 | E53: sí | H53: hecho:barry_presenta, !hecho:conocidas_diana | I53: ana=os, diana=os | J53: ana, diana | M53: hecho conocidas_diana afecto diana ana 4 afecto ana diana 5 log Ana conoció a Diana Barry en La Cuesta del Huerto: la Sra. Barry las presentó. | yo: conocí a Diana Barry en La Cuesta del Huerto. ¡Creo que vamos a ser amigas del alma! | O53: barry, diana | P53: 4 | Q53: barry: Ésta es mi hija Diana. Diana, ¿por qué no llevas a Ana al jardín y le muestras tus flores?
A54: diana_por_casualidad | C54: encuentro | H54: !hecho:conocidas_diana, !hecho:barry_presenta, !hecho:quiere_amiga | M54: hecho conocidas_diana afecto diana ana 2 afecto ana diana 4 log Ana y Diana se conocieron por casualidad. | yo: conocí a Diana Barry, por pura casualidad. Creo que vamos a ser amigas del alma. | N54: quienes: ana, diana | O54: diana | P54: 5 | Q54: diana: Hola… ¿Tú eres la niña que vino a vivir a Tejas Verdes?
A55: broche | B55: gg | D55: 6 | E55: sí | F55: sí | H55: cuaderno:amigas, dias_desde:conocidas_diana:5, !hecho:broche | I55: ana=gg, marilla=gg | J55: marilla | K55: Marilla tiene un broche de amatista que fue de su madre: lo más valioso que posee, y lo usa solo para ir a la iglesia. Y la escuela dominical va a hacer un picnic en el lago, con helado, algo que Ana nunca ha probado. | M55: hecho broche | O55: marilla | P55: 8 | Q55: narra: Marilla tiene un broche de amatista que fue de su madre: lo más valioso que posee, y lo usa solo para ir a la iglesia. Y la escuela dominical va a hacer un picnic en el lago, con helado, algo que Ana nunca ha probado.
A56: zanahorias | B56: es | D56: 7 | E56: sí | F56: sí | H56: !hecho:zanahorias | I56: ana=es, gilbert=es | K56: La escuela de Avonlea tiene una sola sala, para todos los niños del pueblo. Gilbert Blythe es el más listo y el más buen mozo, y está acostumbrado a que todas las niñas lo miren. Ana todavía no lo ha mirado. | M56: hecho zanahorias hecho conoce_gilbert | O56: gilbert | P56: 3 | Q56: narra: La escuela de Avonlea tiene una sola sala, para todos los niños del pueblo. Gilbert Blythe es el más listo y el más buen mozo, y está acostumbrado a que todas las niñas lo miren. Ana todavía no lo ha mirado.
A57: clase_geografia | B57: es | D57: 4 | G57: cada 6 | H57: hora:9.2-12, no_hoy:clase | I57: ana=es, phillips=es | K57: Clase de geografía. El Sr. Phillips señala el mapa del Canadá con una varilla, y las provincias parecen manchas de colores. | M57: hecho clase | O57: phillips | P57: 3 | Q57: narra: Clase de geografía. El Sr. Phillips señala el mapa del Canadá con una varilla, y las provincias parecen manchas de colores.
A58: clase_dictado | B58: es | D58: 4 | G58: cada 6 | H58: hora:9.2-12, no_hoy:clase | I58: ana=es, phillips=es | K58: Dictado. Se oye el rasgueo de las plumas sobre las pizarras, y una mosca que choca contra el vidrio. | M58: hecho clase | O58: phillips | P58: 4 | Q58: narra: Dictado. Se oye el rasgueo de las plumas sobre las pizarras, y una mosca que choca contra el vidrio.
A59: clase_geometria | B59: es | D59: 4 | G59: cada 6 | H59: hora:9.2-12, no_hoy:clase | I59: ana=es, phillips=es | K59: Geometría. En el pizarrón hay un triángulo con letras en las puntas, y para Ana es un misterio tan grande como las pirámides. | M59: hecho clase | O59: phillips | P59: 4 | Q59: narra: Geometría. En el pizarrón hay un triángulo con letras en las puntas, y para Ana es un misterio tan grande como las pirámides.
A60: clase_lectura | B60: es | D60: 4 | G60: cada 6 | H60: hora:9.2-12, no_hoy:clase | I60: ana=es, phillips=es | K60: Lectura en voz alta. Le toca a Ana leer un poema del libro de cuarto grado. | M60: hecho clase | O60: phillips | P60: 5 | Q60: narra: Lectura en voz alta. Le toca a Ana leer un poema del libro de cuarto grado.
A61: clase_composicion_stacy | B61: es | D61: 4 | G61: cada 5 | H61: hora:9.2-12, no_hoy:clase, hecho:llego_stacy | I61: ana=es, stacy=es | K61: La Srta. Stacy abre las ventanas para que entre el aire. «Hoy», dice, «van a escribir sobre algo que vean desde aquí». | M61: hecho clase | O61: stacy | P61: 4 | Q61: narra: La Srta. Stacy abre las ventanas para que entre el aire. «Hoy», dice, «van a escribir sobre algo que vean desde aquí».
A62: clase_botanica_stacy | B62: es | D62: 4 | G62: cada 5 | H62: hora:9.2-12, no_hoy:clase, hecho:llego_stacy | I62: ana=es, stacy=es | K62: Clase de botánica. La Srta. Stacy trajo del bosque un ramo de flores silvestres, y lo pone en un frasco sobre su mesa. | M62: hecho clase | O62: stacy | P62: 3 | Q62: narra: Clase de botánica. La Srta. Stacy trajo del bosque un ramo de flores silvestres, y lo pone en un frasco sobre su mesa.
A63: te_grosella | B63: gg | D63: 7 | E63: sí | H63: tomando_te:ana:diana, !hecho:diana_borracha | I63: ana=gg, diana=gg | K63: Marilla le dio permiso a Ana para invitar a Diana a tomar el té, como dos señoras, con el juego de té bueno y el cordial de frambuesa de la despensa. Pero Marilla no se acordó de que el cordial ya no estaba en la despensa, sino en el sótano. | M63: hecho diana_borracha meta diana estar_en h:os,-,- | Diana se va a su casa, tambaleándose | volver a su casa, mareada | 3 log Ana invitó a Diana a tomar el té y le sirvió, sin saberlo, vino de grosellas en vez de cordial de frambuesa: Diana se fue a su casa… borracha. | yo: invité a Diana a tomar el té y le serví, sin saberlo, vino de grosellas en vez de cordial de frambuesa. ¡Se fue a su casa borracha! | O63: diana | P63: 7 | Q63: narra: Marilla le dio permiso a Ana para invitar a Diana a tomar el té, como dos señoras, con el juego de té bueno y el cordial de frambuesa de la despensa. Pero Marilla no se acordó de que el cordial ya no estaba en la despensa, sino en el sótano.
A64: prohibida | B64: gg | D64: 7 | E64: sí | F64: sí | H64: dias_desde:diana_borracha:1, !hecho:prohibida, !hecho:perdonada | I64: ana=gg, marilla=gg | J64: marilla | K64: La Sra. Barry es una mujer severa, que no perdona fácilmente. Y Diana llegó a su casa mareada, tambaleándose, después de tomar el té en Tejas Verdes. | M64: hecho prohibida triste diana ofensa barry ana vino 0 log La Sra. Barry le prohibió a Diana volver a ver a Ana: el «cordial» era vino de grosellas. | yo: la Sra. Barry le prohibió a Diana volver a verme. Mi corazón está hecho trizas. | O64: marilla | P64: 7 | Q64: narra: La Sra. Barry es una mujer severa, que no perdona fácilmente. Y Diana llegó a su casa mareada, tambaleándose, después de tomar el té en Tejas Verdes.
A65: barry_no_perdona | B65: os | D65: 7 | E65: sí | H65: hecho:prohibida | I65: ana=os, barry=os | O65: barry | P65: 2 | Q65: ana: Sra. Barry, por favor, perdóneme. No sabía que era vino. Me imaginé que era cordial… bueno, creí que era cordial.
A66: crup_aviso | B66: gg | D66: 9 | E66: sí | F66: sí | H66: hecho:prohibida, dias_desde:prohibida:12, !hecho:crup | I66: ana=gg, diana=gg | K66: Una noche de invierno. Casi todos los grandes de Avonlea fueron a Charlottetown, a escuchar el discurso del Primer Ministro: también los Barry. Diana se quedó en casa cuidando a Minnie May, su hermanita de tres años. El crup es una enfermedad de los niños que cierra la garganta: hay que actuar rápido. Ana sabe de crup, porque cuidó a tres pares de mellizos de la Sra. Hammond. | M66: hecho crup meta ana estar_en h:os,-,23 | Ana corre a La Cuesta del Huerto: Minnie May tiene crup | correr a La Cuesta del Huerto: Minnie May tiene crup (cap. 18) | 3 meta diana estar_en h:os,-,23 | Diana vuelve corriendo a su casa | volver corriendo a su casa con Ana | 3 | O66: diana | P66: 5 | Q66: narra: Una noche de invierno. Casi todos los grandes de Avonlea fueron a Charlottetown, a escuchar el discurso del Primer Ministro: también los Barry. Diana se quedó en casa cuidando a Minnie May, su hermanita de tres años.
A67: crup_salva | B67: os | D67: 9 | E67: sí | H67: hecho:crup, hecho:prohibida | I67: ana=os | M67: olvidar prohibida hecho perdonada afecto barry ana 4 afecto diana ana 5 log Ana salvó a Minnie May del crup, toda la noche, con el jarabe de ipecacuana. La Sra. Barry le pidió perdón. | yo: salvé a Minnie May del crup, toda la noche, con el jarabe de ipecacuana. Y la Sra. Barry me pidió perdón. | O67: barry | P67: 6 | Q67: ana: (Minnie May arde de fiebre en el sofá, y apenas puede respirar.)
A68: invita_allan | B68: gg | D68: 5 | F68: sí | H68: cuaderno:escuela_dominical, dias_desde:escuela_dominical:14, presente:sraallan, !hecho:allan_invitados | I68: ana=gg, marilla=gg | K68: Avonlea tiene un pastor nuevo, el Sr. Allan, que llegó con su esposa, joven y alegre. Ana la quiere desde el primer domingo en la escuela dominical. Y en Avonlea, cuando llega un pastor nuevo, cada familia lo invita a tomar el té. | M68: hecho allan_invitados hecho conoce_sraallan | O68: marilla | P68: 3 | Q68: narra: Avonlea tiene un pastor nuevo, el Sr. Allan, que llegó con su esposa, joven y alegre. Ana la quiere desde el primer domingo en la escuela dominical. Y en Avonlea, cuando llega un pastor nuevo, cada familia lo invita a tomar el té.
A69: pastel_linimento | B69: gg | D69: 7 | E69: sí | F69: sí | H69: hecho:allan_invitados, !hecho:pastel_linimento, sentada:sraallan | I69: ana=gg, sraallan=gg | J69: sraallan, marilla | M69: hecho pastel_linimento afecto sraallan ana 5 log Ana le sirvió a la Sra. Allan un pastel con linimento en vez de vainilla; la Sra. Allan fue tan buena que la invitó a la casa parroquial. | yo: le serví a la Sra. Allan un pastel con linimento en vez de vainilla. Ella fue tan buena que me invitó a la casa parroquial. | O69: sraallan, marilla | P69: 7 | Q69: ana: (Ana sirve su pastel en capas, con mermelada roja entre las capas.)
A70: cama_josephine | B70: os | D70: 6 | E70: sí | F70: sí | H70: cuaderno:amigas, !hecho:prohibida, !hecho:cama_josephine, dias_desde:conocidas_diana:15, afecto:diana:ana>=5, letras:ana>=10 | I70: ana=os, diana=os | K70: La tía de la Sra. Barry, la Srta. Josephine Barry, vino desde Charlottetown. Es una anciana rica, muy de mal genio, y se queda en el cuarto de huéspedes de La Cuesta del Huerto. Ana y Diana no lo saben. | M70: hecho cama_josephine afecto josephine ana 5 log Ana y Diana saltaron sobre la cama del cuarto de huéspedes, donde dormía la tía Josephine; Ana confesó y se ganó su amistad. | yo: Diana y yo saltamos sobre la cama de huéspedes, ¡y ahí dormía la tía Josephine! Confesé, y se hizo mi amiga. | O70: diana, josephine | P70: 8 | Q70: narra: La tía de la Sra. Barry, la Srta. Josephine Barry, vino desde Charlottetown. Es una anciana rica, muy de mal genio, y se queda en el cuarto de huéspedes de La Cuesta del Huerto. Ana y Diana no lo saben.
A71: examen_primera | B71: gg | D71: 8 | E71: sí | H71: estacion:verano, dia_estacion:1, dia_juego:56, estudio:ana>=85, !hecho:queens, no_hoy:examen | I71: ana=gg, marilla=gg | K71: El examen de ingreso al Queen's, el colegio de Charlottetown donde se preparan los maestros, se da al comenzar el verano. Los mejores alumnos de toda la Isla compiten por entrar. Ana estudió meses con la Srta. Stacy, y Gilbert Blythe también. | M71: hecho examen hecho queens hecho queens_primera afecto marilla ana 5 afecto matthew ana 5 log Ana dio el examen de ingreso a Queen's en Charlottetown y quedó primera, empatada con Gilbert Blythe. | yo: di el examen de ingreso a Queen's y quedé primera, empatada con Gilbert Blythe. | O71: marilla | P71: 5 | Q71: narra: El examen de ingreso al Queen's, el colegio de Charlottetown donde se preparan los maestros, se da al comenzar el verano. Los mejores alumnos de toda la Isla compiten por entrar. Ana estudió meses con la Srta. Stacy, y Gilbert Blythe también.
A72: examen_entra | B72: gg | D72: 8 | E72: sí | H72: estacion:verano, dia_estacion:1, dia_juego:56, estudio:ana>=50, estudio:ana<85, !hecho:queens, no_hoy:examen | I72: ana=gg, marilla=gg | K72: El examen de ingreso al Queen's, el colegio de Charlottetown donde se preparan los maestros, se da al comenzar el verano. Los mejores alumnos de toda la Isla compiten por entrar. Ana estudió meses con la Srta. Stacy, y Gilbert Blythe también. | M72: hecho examen hecho queens afecto marilla ana 5 log Ana dio el examen de ingreso a Queen's en Charlottetown y entró. | yo: di el examen de ingreso a Queen's, ¡y entré! | O72: marilla | P72: 5 | Q72: narra: El examen de ingreso al Queen's, el colegio de Charlottetown donde se preparan los maestros, se da al comenzar el verano. Los mejores alumnos de toda la Isla compiten por entrar. Ana estudió meses con la Srta. Stacy, y Gilbert Blythe también.
A73: examen_no | B73: gg | D73: 8 | E73: sí | H73: estacion:verano, dia_estacion:1, dia_juego:56, estudio:ana>=20, estudio:ana<50, !hecho:queens, no_hoy:examen | I73: ana=gg, marilla=gg | K73: El examen de ingreso al Queen's, el colegio de Charlottetown donde se preparan los maestros, se da al comenzar el verano. Los mejores alumnos de toda la Isla compiten por entrar. Ana estudió meses con la Srta. Stacy, y Gilbert Blythe también. | M73: hecho examen triste ana log Ana dio el examen de ingreso a Queen's en Charlottetown, pero no le alcanzó. El año que viene, otra vez. | yo: di el examen de ingreso a Queen's, pero no me alcanzó. El año que viene, otra vez. | O73: marilla | P73: 5 | Q73: narra: El examen de ingreso al Queen's, el colegio de Charlottetown donde se preparan los maestros, se da al comenzar el verano. Los mejores alumnos de toda la Isla compiten por entrar. Ana estudió meses con la Srta. Stacy, y Gilbert Blythe también.
A74: inicio_llegada | B74: gg | D74: 10 | E74: sí | H74: hecho:inicio_juego, !hecho:llegada_tv | I74: ana=gg, marilla=gg | J74: matthew, marilla | K74: Avonlea, un pueblito de granjas en la Isla del Príncipe Eduardo, en Canadá, a fines del siglo XIX. En la granja de Tejas Verdes viven dos hermanos solterones, Matthew y Marilla Cuthbert. Ya están mayores, y le pidieron a la Sra. Spencer que les trajera del orfanato un niño, para ayudar en el campo. Pero en la estación de Bright River, Matthew no encontró a ningún niño: lo esperaba una niña flaca, de pelo rojo, con un sombrero de paja y una maleta vieja. Matthew no se atrevió a dejarla allí. Ahora llegan juntos a Tejas Verdes, ya de noche, y Marilla los está esperando en la puerta de la cocina. | L74: log Ana llegó a Tejas Verdes con Matthew, de noche. Marilla esperaba a un niño. | M74: hecho llegada_tv hecho primera_noche log Marilla dejó que Ana se quedara esa noche, hasta aclarar el enredo. Ana casi no probó la cena. | yo: Marilla me dejó quedarme esa noche, hasta aclarar el enredo. Casi no probé la cena. | N74: narra salvo: hecho:desde_estacion lineas: libro:llegada | O74: matthew, marilla | P74: 35 | Q74: narra: Avonlea, un pueblito de granjas en la Isla del Príncipe Eduardo, en Canadá, a fines del siglo XIX. En la granja de Tejas Verdes viven dos hermanos solterones, Matthew y Marilla Cuthbert. Ya están mayores, y le pidieron a la Sra. Spencer que les trajera del orfanato un niño, para ayudar en el campo.
A75: primera_noche_sube | B75: gg | D75: 9 | E75: sí | H75: hecho:primera_noche, !hecho:desayuno_prueba, !dicha:primera_bed, hora:21-29, horas_desde:llegada_tv:0.5 | K75: Ya es noche cerrada. Marilla toma la vela, busca a Ana y la lleva hasta la pieza del alero, sin decir palabra. | M75: a_pieza | P75: 1 | Q75: narra: Ya es noche cerrada. Marilla toma la vela, busca a Ana y la lleva hasta la pieza del alero, sin decir palabra.
A76: primera_bed | B76: ana_sola | C76: primera | H76: hecho:primera_noche, !hecho:desayuno_prueba, !hecho:se_queda | J76: marilla | O76: marilla | P76: 18 | Q76: ana: (La pieza del alero: paredes blancas y desnudas, una cama alta, una mesita, una silla. Ana la mira con espanto.)
A77: primera_noche | B77: gg | D77: 10 | E77: sí | H77: hecho:llegada_tv, !hecho:primera_noche, !capitulo | I77: ana=gg, marilla=gg | J77: matthew, marilla | M77: hecho primera_noche log Marilla dejó que Ana se quedara esa noche, hasta aclarar el enredo. | yo: Marilla me dejó quedarme esa noche, hasta aclarar el enredo. | O77: marilla, matthew | P77: 9 | Q77: marilla: Bueno, bueno, no hace falta llorar así. No te vamos a echar esta noche. Te quedas hasta que aclaremos este enredo. ¿Cómo te llamas?
A78: lynde_se_entera | B78: rl | D78: 2 | H78: hecho:inicio_juego, hecho:desayuno_prueba, hora:7-12, !sabe:lynde:nina_cuthbert | K78: Anoche, desde su ventana, la Sra. Rachel Lynde vio pasar la calesa de Matthew… y en ella, una niña de trenzas rojas. Esta mañana, antes de que el sol esté alto, ya se lo ha contado a medio Avonlea. A la otra mitad se lo contará en la tarde. | L78: saber lynde nina_cuthbert | P78: 1 | Q78: narra: Anoche, desde su ventana, la Sra. Rachel Lynde vio pasar la calesa de Matthew… y en ella, una niña de trenzas rojas. Esta mañana, antes de que el sol esté alto, ya se lo ha contado a medio Avonlea. A la otra mitad se lo contará en la tarde.
A79: desayuno_prueba | B79: gg | D79: 9 | E79: sí | H79: hecho:primera_noche, dias_desde:llegada_tv:1, !hecho:desayuno_prueba, hora:6.5-14 | J79: marilla | K79: Huele a pan tostado en toda la casa. Marilla llama: «¡Ana! ¡El desayuno!». | L79: a_cocina punto viaje | Volver a la mañana del viaje a White Sands | M79: hecho desayuno_prueba | N79: donde: tejas | O79: marilla | P79: 16 | Q79: narra: Huele a pan tostado en toda la casa. Marilla llama: «¡Ana! ¡El desayuno!».
A80: viaje_spencer | B80: gg | D80: 9 | E80: sí | H80: hecho:desayuno_prueba, !hecho:a_prueba, hora:14-19, paciencia:marilla:ana>=1 | J80: marilla | K80: White Sands está a unas millas por el camino de la costa. Allí vive la Sra. Spencer, la que trajo a Ana del orfanato por equivocación: Marilla va a pedirle que la devuelva. Ana sabe que puede ser su último día en Tejas Verdes. | L80: a_cocina | M80: hecho conoce_blewett hecho a_prueba suma afecto:marilla:ana 1 log Marilla llevó a Ana a White Sands; la Sra. Blewett la quería de sirvienta, y Marilla no se la dio. Esa noche le dijo a Matthew que se la quedaba; a Ana, todavía no. | yo: Marilla me llevó a White Sands. La Sra. Blewett me quería de sirvienta, pero Marilla no me entregó. | N80: donde: tejas | O80: marilla | P80: 11 | Q80: narra: White Sands está a unas millas por el camino de la costa. Allí vive la Sra. Spencer, la que trajo a Ana del orfanato por equivocación: Marilla va a pedirle que la devuelva. Ana sabe que puede ser su último día en Tejas Verdes.
A81: llamar_almuerzo | B81: gg | D81: 4 | G81: dia | H81: hecho:desayuno_prueba, hora:12-13.4, no_hoy:llamada_almuerzo | I81: ana=gg, marilla=gg | J81: marilla | L81: hecho llamada_almuerzo | O81: marilla | P81: 2 | Q81: marilla: Ana, a la mesa. La comida no se va a quedar esperando a que termines de imaginar.
A82: llamar_almuerzo_afuera | B82: gg | D82: 4 | G82: dia | H82: hecho:desayuno_prueba, hora:12-13.4, no_hoy:llamada_almuerzo | I82: ana=out | K82: Desde la puerta de la cocina, Marilla se seca las manos en el delantal y llama: «¡Ana! ¡A la mesa!» | L82: hecho llamada_almuerzo | N82: donde: casa | P82: 2 | Q82: narra: Desde la puerta de la cocina, Marilla se seca las manos en el delantal y llama: «¡Ana! ¡A la mesa!»
A83: marilla_a_la_cama | B83: gg | D83: 5 | G83: dia | H83: hecho:a_prueba, hora:21-23.5 | K83: Ya es de noche en Tejas Verdes. Marilla se asoma con la vela: «Ana, a la cama. Mañana hay que madrugar.» | N83: donde: tejas | P83: 2 | Q83: narra: Ya es de noche en Tejas Verdes. Marilla se asoma con la vela: «Ana, a la cama. Mañana hay que madrugar.»
A84: falta_camison | B84: gg | D84: 6 | G84: dia | H84: hecho:desayuno_prueba, ana:camison, ve:marilla, hora:9-19 | J84: marilla | O84: marilla | P84: 2 | Q84: marilla: ¡Ana! ¿Todavía en camisón a esta hora? En esta casa una se viste apenas se levanta.
A85: falta_ropa | B85: gg | D85: 6 | G85: dia | H85: hecho:ropa_tirada_otra, ve:marilla, hora:6-13 | J85: marilla | O85: marilla | P85: 2 | Q85: marilla: Otra vez la ropa por el suelo, Ana. ¿No habíamos quedado en que la doblabas en la silla?
A86: camison_barry | B86: os | D86: 6 | G86: dia | H86: ana:camison, !donde:ana:tejas, ve:barry, sabe:barry:nina_cuthbert, !comento:barry:ana:camison, hora:7-21 | J86: barry | M86: contar barry ana_en_camison | O86: barry | P86: 1 | Q86: barry: (La Sra. Barry se lleva la mano al pecho.) ¡Niña! ¿Andas en camisón por las casas ajenas? ¡Qué va a decir la gente! Ya hablaré con Marilla.
A87: camison_lynde | B87: rl | D87: 6 | G87: dia | H87: ana:camison, !donde:ana:tejas, ve:lynde, sabe:lynde:nina_cuthbert, !comento:lynde:ana:camison, hora:7-21 | J87: lynde | M87: contar lynde ana_en_camison | O87: lynde | P87: 1 | Q87: lynde: ¡Habráse visto! ¡La huérfana de los Cuthbert, en camisón por el camino! Esto lo sabe Marilla antes de que se ponga el sol, como que me llamo Rachel Lynde.
A88: marilla_sabe_camison | B88: gg | D88: 6 | H88: sabe:marilla:ana_en_camison:contada, !sabe:marilla:ana_en_camison:2, ve:marilla | J88: marilla | O88: marilla | P88: 2 | Q88: marilla: Ana. Me vino a contar alguien que andabas en camisón por Avonlea. En camisón. ¿Tienes idea de lo que va a decir la gente?
A89: marilla_sabe_noche | B89: gg | D89: 6 | H89: sabe:marilla:ana_de_noche:contada, ve:marilla, hora:6-21 | J89: marilla | O89: marilla | P89: 2 | Q89: marilla: Ana. Alguien me dijo que anoche te vieron sola por el camino, a esas horas. ¿Es cierto?
A90: marilla_sabe_sombrero | B90: gg | D90: 6 | H90: sabe:marilla:ana_sin_sombrero:contada, ve:marilla, !donde:ana:ig | J90: marilla | O90: marilla | P90: 2 | Q90: marilla: Ana Shirley. Alguien me contó que fuiste a la iglesia sin sombrero. ¡A la iglesia! ¿Qué va a pensar el reverendo de cómo te crío?
A91: marilla_sabe_camison_descalza | B91: gg | D91: 6 | H91: sabe:marilla:ana_en_camison:2, !sabe:marilla:ana_en_camison:3, !dicha:marilla_sabe_camison, ve:marilla | J91: marilla | O91: marilla | P91: 2 | Q91: marilla: Ana Shirley. Alguien me dice que anduviste en camisón por todo Avonlea, y descalza. ¡Descalza, con este tiempo!
A92: marilla_sabe_camison_cementerio | B92: gg | D92: 6 | H92: sabe:marilla:ana_en_camison:3, ve:marilla | J92: marilla | O92: marilla | P92: 3 | Q92: marilla: Ana. Ahora dicen en Avonlea que sales de noche en camisón a bailar en el cementerio. ¿Me quieres explicar de dónde sacan eso?
A93: falta_noche | B93: gg | D93: 9 | E93: sí | G93: dia | H93: hecho:desayuno_prueba, !donde:ana:tejas, hora:21.5-29 | K93: Ya es noche cerrada y Ana no ha vuelto. Marilla enciende el farol y sale a buscarla por los caminos, con el chal sobre los hombros y la boca apretada. La encuentra, y la trae a casa sin decir una palabra. | L93: suma paciencia:marilla:ana -1 contar marilla ana_de_noche | M93: a_pieza | P93: 2 | Q93: narra: Ya es noche cerrada y Ana no ha vuelto. Marilla enciende el farol y sale a buscarla por los caminos, con el chal sobre los hombros y la boca apretada. La encuentra, y la trae a casa sin decir una palabra.
A94: falta_viaje | B94: gg | D94: 10 | E94: sí | H94: hecho:desayuno_prueba, !hecho:a_prueba, !donde:ana:tejas, hora:14.5-19 | K94: Marilla tiene la calesa lista para ir a White Sands, y Ana no aparece por ninguna parte. La busca por la granja, por el huerto, por el camino… y la encuentra lejos, muy lejos. Vuelven a Tejas Verdes en un silencio que da miedo. | L94: suma paciencia:marilla:ana -1 | M94: a_cocina | P94: 1 | Q94: narra: Marilla tiene la calesa lista para ir a White Sands, y Ana no aparece por ninguna parte. La busca por la granja, por el huerto, por el camino… y la encuentra lejos, muy lejos. Vuelven a Tejas Verdes en un silencio que da miedo.
A95: viaje_spencer_duda | B95: gg | D95: 9 | E95: sí | H95: hecho:desayuno_prueba, !hecho:a_prueba, hora:14-19, paciencia:marilla:ana<1 | J95: marilla | K95: White Sands está a unas millas por el camino de la costa. Marilla lleva las riendas y no dice nada en todo el viaje: piensa en el camisón a mediodía, en la ropa por el suelo, en lo que ha tenido que aguantar. Ana tampoco habla. Mira el mar y aprieta su maleta vieja. | L95: a_cocina | M95: hecho conoce_blewett hecho blewett_duda | N95: donde: tejas | P95: 4 | Q95: narra: White Sands está a unas millas por el camino de la costa. Marilla lleva las riendas y no dice nada en todo el viaje: piensa en el camisón a mediodía, en la ropa por el suelo, en lo que ha tenido que aguantar. Ana tampoco habla. Mira el mar y aprieta su maleta vieja.
A96: duda_matthew | B96: gg | D96: 9 | E96: sí | H96: hecho:blewett_duda, !hecho:a_prueba, afecto:matthew:ana>=4 | J96: marilla | K96: «No puedo decidir sin hablarlo con Matthew», dice al fin Marilla. Vuelven a Tejas Verdes ya de tarde. Esa noche, en el corral, Matthew escucha todo sin interrumpir, y después dice, muy bajito: «Bueno, pues… yo creo que podríamos quedarnos con ella, Marilla. Podríamos hacerle algún bien.» Y Marilla, que estaba decidida a devolverla, cede. | L96: a_cocina | M96: hecho a_prueba log Marilla casi le dio Ana a la Sra. Blewett; Matthew pidió que se quedara. | yo: Marilla casi me entregó a la Sra. Blewett, pero Matthew pidió que me quedara. | P96: 3 | Q96: narra: «No puedo decidir sin hablarlo con Matthew», dice al fin Marilla. Vuelven a Tejas Verdes ya de tarde. Esa noche, en el corral, Matthew escucha todo sin interrumpir, y después dice, muy bajito: «Bueno, pues… yo creo que podríamos quedarnos con ella, Marilla. Podríamos hacerle algún bien.» Y Marilla, que estaba decidida a devolverla, cede.
A97: duda_suplica | B97: gg | D97: 8 | E97: sí | H97: hecho:blewett_duda, !hecho:a_prueba, hecho:blewett_suplica, afecto:marilla:ana>=2 | J97: marilla | K97: Marilla mira esa manito aferrada a su manga, y algo se le quiebra por dentro. «No», dice. «No puedo. Me la llevo de vuelta.» La Sra. Blewett se encoge de hombros. En la calesa, Ana llora todo el camino, de puro alivio. | L97: a_cocina | M97: hecho a_prueba log Ana le suplicó a Marilla en White Sands, y Marilla no la entregó. | yo: le supliqué a Marilla en White Sands, y no me entregó. | P97: 3 | Q97: narra: Marilla mira esa manito aferrada a su manga, y algo se le quiebra por dentro. «No», dice. «No puedo. Me la llevo de vuelta.» La Sra. Blewett se encoge de hombros. En la calesa, Ana llora todo el camino, de puro alivio.
A98: duda_calla | B98: gg | D98: 7 | E98: sí | H98: hecho:blewett_duda, !hecho:a_prueba, hecho:blewett_calla, afecto:marilla:ana>=3 | J98: marilla | K98: Marilla ve esa carita pálida que no pide nada, y se acuerda de lo que Ana le contó en el camino: la Sra. Thomas, los mellizos, el orfanato. «No», dice de pronto. «Me la llevo de vuelta.» | L98: a_cocina | M98: hecho a_prueba | P98: 3 | Q98: narra: Marilla ve esa carita pálida que no pide nada, y se acuerda de lo que Ana le contó en el camino: la Sra. Thomas, los mellizos, el orfanato. «No», dice de pronto. «Me la llevo de vuelta.»
A99: devuelta_blewett | B99: gg | D99: 1 | E99: sí | H99: hecho:blewett_duda, !hecho:a_prueba | K99: Marilla aprieta los labios y asiente. Esa misma tarde, Ana se va con la Sra. Blewett, con su maleta vieja y su sombrero de paja. No mira hacia atrás, porque si mira hacia atrás va a llorar. En Tejas Verdes, Matthew no dice nada durante días. | M99: hecho devuelta log Marilla le entregó Ana a la Sra. Blewett. | yo: Marilla me entregó a la Sra. Blewett. final devuelta | Ana se fue con la Sra. Blewett. En el libro, Marilla no la entregó: Ana se ganó, poco a poco, su lugar en Tejas Verdes. | P99: 1 | Q99: narra: Marilla aprieta los labios y asiente. Esa misma tarde, Ana se va con la Sra. Blewett, con su maleta vieja y su sombrero de paja. No mira hacia atrás, porque si mira hacia atrás va a llorar. En Tejas Verdes, Matthew no dice nada durante días.
A100: se_queda | B100: gg | D100: 9 | E100: sí | F100: sí | H100: hecho:a_prueba, !hecho:se_queda, dias_desde:a_prueba:1, hora:14-19 | J100: marilla | K100: «Por razones que solo ella sabía, Marilla no le dijo a Ana que se quedaba en Tejas Verdes hasta la tarde siguiente.» Ana se ha pasado el día con el corazón en la boca, sin atreverse a preguntar. | L100: a_cocina | M100: hecho se_queda suma afecto:marilla:ana 1 log Marilla le dijo a Ana que se queda en Tejas Verdes, para siempre. | yo: Marilla me dijo que me quedo en Tejas Verdes. ¡Para siempre! | N100: donde: tejas | O100: marilla | P100: 7 | Q100: narra: «Por razones que solo ella sabía, Marilla no le dijo a Ana que se quedaba en Tejas Verdes hasta la tarde siguiente.» Ana se ha pasado el día con el corazón en la boca, sin atreverse a preguntar.
A101: primera_gwin | B101: ana_sola | C101: primera | P101: 5 | Q101: ana: (Ana corre a la ventana y la abre de par en par. Afuera, un cerezo enorme, todo blanco de flores, le roza el marco.)
A102: primera_mirror | B102: ana_sola | C102: primera | P102: 3 | Q102: ana: (Ana se mira en el espejito. Una cara angosta, llena de pecas, unos ojos grandes y grises… y ese pelo.)
A103: primera_armario | B103: ana_sola | C103: primera | N103: tambien | P103: 2 | Q103: ana: ¡Un armario! Nunca tuve un armario para mí sola. En el orfanato teníamos un clavo cada una, y a veces ni eso.
A104: primera_geranio | B104: ana_sola | C104: primera | H104: ve:marilla | O104: marilla | P104: 7 | Q104: ana: (Ana se acerca a la ventana de la cocina. En una maceta, un geranio con olor a manzana, lleno de flores rojas.)
...

Sheet Noticias
A1: Noticia | B1: Qué es | C1: La saben desde el principio | D1: La saben desde que… (condiciones: quiénes) | E1: Al conocer a Ana | F1: Le llega a (quién: horas) | G1: Se cuenta por (días) | H1: Cómo se cuenta | I1: Cómo la cuenta cada uno (quién: texto) | J1: Versiones exageradas (una por línea, en orden) | K1: Respuestas
A2: huerfano | B2: los Cuthbert van a traer un niño del orfanato | C2: marilla, matthew, spencer | G2: 1 | H2: ¿Supo? ¡Los Cuthbert van a traer un niño del orfanato! A su edad... ya les dije que es un riesgo. | I2: lynde: ¿Supo? ¡Los Cuthbert van a traer un huérfano de Nueva Escocia! Yo se lo dije a Marilla: es un riesgo. | K2: ¿Un huérfano? ¿Marilla Cuthbert? ¡Quién lo diría!
A3: nina_cuthbert | B3: los Cuthbert, que pidieron un niño, tienen una niña | C3: marilla, matthew, spencer | E3: sí | G3: 6 | H3: ¿Supo lo de los Cuthbert? ¡Pidieron un niño al orfanato y les llegó una niña! Pelirroja, dicen. | I3: lynde: ¿Supo lo de los Cuthbert? ¡Pidieron un niño y les llegó una niña! Pelirroja, dicen. Yo siempre dije que eso de traer huérfanos… niños: ¿Sabías? ¡En Tejas Verdes hay una niña nueva! Del orfanato. Y es pelirroja, pelirroja como una zanahoria. | K3: ¿Una niña? ¿Y qué van a hacer los Cuthbert con una niña? ¡No me diga! ¿Y Marilla qué dice?
A4: ana_en_camison | B4: la niña de los Cuthbert anda en camisón por Avonlea | F4: marilla: 3 | G4: 10 | H4: ¿Supo que la niña de los Cuthbert anda en camisón por las casas? ¡En camisón! | I4: niños: ¿Sabías que la niña nueva de Tejas Verdes salió en camisón a la calle? ¡En camisón! Mi mamá dice que eso no se hace. | J4: ¿Supo? ¡La niña de los Cuthbert anda en camisón por todo Avonlea, y descalza! Con este frío. Dicen que la niña de los Cuthbert sale de noche en camisón, descalza, a bailar en el cementerio. ¡Yo no digo nada! | K4: ¡Qué vergüenza! Marilla debe estar furiosa.
A5: cerdo_pye | B5: a los Pye se les escapó otra vez el cerdo | C5: lynde | H5: ¿Supo que a los Pye se les escapó otra vez el cerdo? Yo siempre lo dije. | I5: niños: ¡Se les escapó el chancho a los Pye otra vez! Lo vi correr por el camino.
A6: maestra_plumas | B6: la maestra nueva usa sombrero con plumas | D6: hecho:llego_stacy: lynde, srapye | G6: 14 | H6: Dicen que la maestra nueva usa sombrero con plumas. ¡Plumas, en una escuela!
A7: loro_harrison | B7: el loro del Sr. Harrison dice cosas terribles | C7: lynde | H7: Yo no soy de las que hablan, pero el loro del Sr. Harrison dice cada cosa...
A8: rastrillo_matthew | B8: Matthew Cuthbert compró un rastrillo en invierno | D8: estacion:invierno: lynde | H8: Matthew Cuthbert fue a la tienda y salió con un rastrillo. ¡En pleno invierno!
A9: ana_lengua | B9: la niña de los Cuthbert tiene una lengua, pero buen corazón | D9: hecho:lynde_visita, !hecho:ofendio_lynde: lynde | H9: ¡Esa niña de los Cuthbert! Pelirroja y con una lengua... aunque buen corazón tiene, eso sí.
A10: ana_ofendio_lynde | B10: la niña de los Cuthbert le dijo vieja chismosa a la Sra. Lynde | D10: hecho:ofendio_lynde: lynde | H10: ¡Esa niña de los Cuthbert! Me dijo vieja chismosa en mi propia cara. ¡A mí! | J10: ¿Supo? La niña de los Cuthbert le gritó a Rachel Lynde que era una vieja gorda y chismosa, ¡y pataleando! | K10: ¡Qué niña! ¿Y qué hizo Marilla?
A11: vendio_vaca | B11: Ana vendió una vaca | H11: ¿Supo que la niña de los Cuthbert vendió una vaca? ¡Una niña vendiendo vacas! | J11: Dicen que la niña de los Cuthbert vendió la vaca del Sr. Harrison, ¡y con la plata se compró un sombrero!
A12: pastor_nuevo | B12: llegó un pastor nuevo, el Sr. Allan, con su esposa | D12: hecho:llego_allan: lynde, barry, srapye | G12: 14 | H12: ¿Ya vio al pastor nuevo? El Sr. Allan. Y la esposa, tan joven... a ver si sabe llevar una casa parroquial. | I12: lynde: El pastor nuevo predica bien, no digo que no. Pero la esposa es una niña. ¡Una niña, en la casa parroquial!
A13: tia_josephine | B13: la tía Josephine de los Barry vino de Charlottetown | D13: presente:josephine: barry, diana, lynde | G13: 7 | H13: La tía Josephine de los Barry está de visita. Rica, y con un genio... que Dios nos libre.
A14: se_va_phillips | B14: el Sr. Phillips se va de la escuela de Avonlea | D14: hecho:se_fue_phillips: lynde, barry, srapye, josie | G14: 10 | H14: ¿Supo que el Sr. Phillips se fue? En la despedida lloraron todas las niñas, hasta las que no lo querían. | J14: Dicen que en la despedida del Sr. Phillips lloró toda la escuela, y Prissy Andrews se desmayó. ¡Se desmayó!
A15: ana_de_noche | B15: la niña de los Cuthbert anda sola por los caminos de noche | F15: marilla: 4 | G15: 7 | H15: ¿Supo que vieron a la niña de los Cuthbert sola por el camino, de noche? ¡A esas horas! | J15: Dicen que la niña de los Cuthbert sale todas las noches, sola, a mirar la luna. ¡Como una gitana! | K15: ¡Sola, de noche! Marilla tendría que tenerla más cortita.
A16: ana_sin_sombrero | B16: la niña de los Cuthbert fue a la iglesia sin sombrero | F16: marilla: 3 | G16: 7 | H16: ¿Vio a la niña de los Cuthbert en la iglesia? ¡Sin sombrero! En la casa del Señor. | J16: Dicen que la niña de los Cuthbert fue a la iglesia despeinada y sin sombrero, ¡y cantó más fuerte que nadie!

Sheet Llegadas
A1: Quién | B1: De visita | C1: Llega si… (una alternativa por línea) | D1: Se va si… (una por línea) | E1: Al llegar (diario) | F1: Al irse (diario)
A2: diana | C2: dias_desde:llegada_tv:17 | E2: Diana Barry volvió de Carmody, donde su tía.
A3: gilbert | C3: dias_desde:escuela:4 estacion:invierno | E3: Gilbert Blythe volvió de Nuevo Brunswick.
A4: josephine | B4: sí | C4: estacion:invierno | E4: La tía Josephine llegó de Charlottetown a La Cuesta del Huerto. | F4: La tía Josephine se volvió a Charlottetown.
A5: allan | C5: estacion:primavera, dias_desde:se_fue_josephine:7 | E5: Llegó el pastor nuevo, el Sr. Allan, con su esposa.
A6: sraallan | C6: estacion:primavera, dias_desde:se_fue_josephine:7
A7: phillips | D7: estacion:verano, hecho:llego_josephine | F7: El Sr. Phillips se despidió de la escuela: todas las niñas lloraron.
A8: prissy | D8: hecho:se_fue_phillips | F8: Prissy Andrews se fue a Queen's.
A9: stacy | C9: estacion:otoño, hecho:se_fue_phillips | E9: Llegó la maestra nueva, la Srta. Stacy.
A10: buhonero | B10: sí | C10: dia_estacion:4 dia_estacion:11
A11: veraneante | B11: sí | C11: estacion:verano

Sheet Diálogos
A1: Escena | B1: Quién | C1: Qué dice (o hace)
A2: rachel_ventana | B2: lynde | C2: ¡Matthew Cuthbert, con cuello blanco y en la calesa! ¿Adónde irá? No me quedo tranquila: voy ahora mismo a Tejas Verdes.
A3: mesa_tres | B3: marilla | C3: Tres platos. Matthew, yo… y el niño.
A4: avenida | B4: ana | C4: (Ana enmudece. Se queda mirando la bóveda de flores, con las manos juntas, como si estuviera en una iglesia.)
A5: avenida | B5: matthew | C5: (Matthew la mira de reojo. No dice nada, para no romper el encanto.)
A6: avenida | B6: ana | C6: (…)
A7: newbridge | B7: ana | C7: (Callada todavía. Los perros les ladran, los chicos gritan desde las cercas, hay caras curiosas en las ventanas: Ana no ve nada de eso.)
A8: avenida_petalos | B8: ana | C8: (Ana echa la cabeza atrás para mirar la bóveda de flores. Los pétalos le caen en el pelo y no se los quita.)
A9: avenida_paso | B9: matthew | C9: (Matthew afloja las riendas. La yegua va al paso, como si también ella quisiera que esto no se acabara.)
A10: avenida_roseton | B10: ana | C10: (Al fondo de la Avenida, el cielo del atardecer brilla como el rosetón de una catedral.)
A11: newbridge_ventanas | B11: ana | C11: (Las ventanas del pueblo se encienden una a una. Ana sigue mirando hacia atrás, hacia donde quedó la Avenida.)
A12: silencio_manos | B12: ana | C12: (Ana va callada, con las manos juntas sobre el bolso de alfombra y los ojos en el cielo del oeste.)
... A828: lugar_primera_nieve | B828: ana | C828: ¡La primera nieve! El Camino Blanco se acordó de su nombre. Cada copo es distinto, dicen en la escuela. Como las personas. Como las amigas del alma.

Sheet Hechos
A1: Hecho | B1: Lo dejan | C1: Lo piden | D1: Estado
A2: a_prueba | B2: escena viaje_spencer, escena duda_matthew, escena duda_suplica, escena duda_calla | C2: escena marilla_a_la_cama, escena se_queda, escena ventana_a_prueba, escena conv_marilla_vestidos, charla par:ana+marilla:0, charla par:ana+marilla:1, charla par:ana+matthew:0, charla par:marilla+matthew:0, una frase de blewett, meta quedarse (pista), hito a_prueba
A3: allan_invitados | B3: escena invita_allan | C3: escena pastel_linimento, escena iglesia_allan, meta allan (pista)
A4: amigas | C4: hito amiga_del_alma
A5: ana | C5: escena camison_barry, escena camison_lynde, escena marilla_sabe_sombrero, escena falta_noche, escena falta_viaje, una frase de matthew, una frase de marilla, una frase de diana, una frase de barry, una frase de harrison, una frase de allan, una frase de sraallan, una frase de stacy, una frase de vecino, una frase de adultos, una frase de niños, noticia ana_en_camison, noticia ana_de_noche
A6: ana_admite_gilbert | B6: escena conv_diana_gilbert_contesta (una opción) | D6: nadie lo lee
A7: barry | C7: escena camison_barry, una frase de barry
A8: barry_presenta | B8: escena barry_recibe | C8: escena conoce_diana, una frase de barry
A9: blewett_calla | B9: escena viaje_spencer_duda (una opción) | C9: escena duda_calla
A10: blewett_duda | B10: escena viaje_spencer_duda | C10: escena duda_matthew, escena duda_suplica, escena duda_calla, escena devuelta_blewett
A11: blewett_orgullo | B11: escena viaje_spencer_duda (una opción) | D11: nadie lo lee
A12: blewett_suplica | B12: escena viaje_spencer_duda (una opción) | C12: escena duda_suplica
A13: broche | B13: escena broche | C13: meta picnic, hito confianza_marilla
A14: broche_confeso | B14: escena broche (una opción) | C14: hito confianza_marilla
A15: broche_verdad | B15: escena broche (una opción) | C15: hito confianza_marilla
A16: cama_josephine | B16: escena cama_josephine | C16: escena conv_diana_tia, una frase de josephine
A17: clase | B17: escena clase_geografia, escena clase_dictado, escena clase_geometria, escena clase_lectura, escena clase_composicion_stacy, escena clase_botanica_stacy | C17: escena clase_geografia, escena clase_dictado, escena clase_geometria, escena clase_lectura, escena clase_composicion_stacy, escena clase_botanica_stacy
A18: conoce_ | B18: código | D18: nadie lo lee
A19: conoce_barry | C19: una frase de barry
A20: conoce_blewett | B20: escena viaje_spencer, escena viaje_spencer_duda | D20: nadie lo lee
A21: conoce_charlie | C21: una frase de charlie
A22: conoce_gertie | C22: una frase de gertie
A23: conoce_gilbert | B23: escena zanahorias | C23: una frase de gilbert
A24: conoce_harrison | C24: una frase de harrison
A25: conoce_jane | C25: escena conv_jane_maestra, una frase de jane
A26: conoce_josie | C26: escena conv_josie_cerca
A27: conoce_lawson | C27: una frase de lawson
A28: conoce_lynde | C28: una frase de lynde
A29: conoce_minnie | C29: escena conv_minnie_cuento, una frase de minnie
A30: conoce_phillips | C30: escena conv_phillips_libro
A31: conoce_ruby | C31: escena conv_ruby_muchachos
A32: conoce_sara | C32: una frase de sara
A33: conoce_sraallan | B33: escena invita_allan | C33: escena conv_sraallan_ser_buena, una frase de sraallan, código
A34: conoce_stacy | C34: escena espejo_estudio, escena conv_marilla_queens, escena conv_matthew_queens, escena conv_diana_futuro, escena conv_stacy_queens, escena conv_stacy_escribir, una frase de stacy, meta queens (pista), código
A35: conocidas_diana | B35: escena conoce_diana, escena diana_por_casualidad, código | C35: escena quiere_amiga, escena aviso_barry, escena barry_recibe, escena conoce_diana, escena diana_por_casualidad, una frase de diana, meta conocer_diana, código
A36: conv_marilla_oraciones | C36: una frase de marilla
A37: crup | B37: escena crup_aviso | C37: escena crup_salva, meta perdon_barry (pista)
A38: desayuno_prueba | B38: escena desayuno_prueba | C38: escena lynde_se_entera, escena viaje_spencer, escena llamar_almuerzo, escena llamar_almuerzo_afuera, escena falta_camison, escena falta_noche, escena falta_viaje, escena viaje_spencer_duda, escena primera_stairs
A39: desde_estacion | B39: código | C39: escena inicio_llegada (narra salvo)
A40: devuelta | B40: escena devuelta_blewett | C40: hito decision
A41: diana_borracha | B41: escena te_grosella | C41: escena prohibida, meta perdon_barry, hito amistad_a_prueba
A42: disculpa_lynde | B42: escena lynde_disculpa | C42: hito humillada, hito pedir_perdon
A43: escuela | C43: una frase de gertie
A44: examen | B44: escena examen_primera, escena examen_entra, escena examen_no | C44: meta queens (pista)
A45: historia_ | B45: código | C45: código
A46: historia_a_prueba | B46: hitos
A47: historia_a_prueba_cerrado | B47: hitos
A48: historia_amiga_del_alma | B48: hitos
A49: historia_amiga_del_alma_cerrado | B49: hitos
A50: historia_amiga_del_alma_juran | B50: hitos
A51: historia_amiga_del_alma_no_juran | B51: hitos
A52: historia_amistad_a_prueba | B52: hitos
A53: historia_amistad_a_prueba_cerrado | B53: hitos
A54: historia_amistad_a_prueba_la_recupera | B54: hitos
A55: historia_confianza_marilla | B55: hitos
A56: historia_confianza_marilla_cerrado | B56: hitos
A57: historia_confianza_marilla_confiesa_en_falso | B57: hitos
... A95: hito_paciencia_4 | B95: habilidad paciencia
A96: inicio_juego | B96: código | C96: código
A97: invierno | C97: escena banco_lago_atardecer, escena lugar_bosque_manana, escena lugar_puente, escena lugar_lago_niebla, escena lugar_campo_rosado, escena lugar_playa, escena lugar_rio_escuela, escena lugar_granero, escena lugar_iglesia, escena lugar_corral_idlewild, escena conv_matthew_huerta
A98: llamada_almuerzo | B98: escena llamar_almuerzo, escena llamar_almuerzo_afuera | C98: escena llamar_almuerzo, escena llamar_almuerzo_afuera
A99: llegada_tv | B99: escena llegada, escena inicio_llegada | C99: escena primera_noche, escena desayuno_prueba, escena lugar_aldea, una frase de lawson, una frase de vecino, llegadas de diana, hito llegada
A100: llegaron | B100: código | C100: escena llegada
A101: llego_ | B101: código | C101: código
A102: llego_allan | B102: llegadas | C102: noticia pastor_nuevo
A103: llego_buhonero | B103: llegadas
A104: llego_diana | B104: llegadas
A105: llego_gilbert | B105: llegadas | C105: charla par:ana+diana:5
A106: llego_josephine | B106: llegadas | C106: llegadas de phillips
A107: llego_sraallan | B107: llegadas
A108: llego_stacy | B108: llegadas | C108: charla par:lynde+marilla:3, una frase de carrie, noticia maestra_plumas
A109: llego_veraneante | B109: llegadas
A110: lynde | C110: escena lynde_se_entera, escena camison_lynde, una frase de lynde
A111: lynde_contenida | B111: escena lynde_visita (una opción) | C111: hito humillada
A112: lynde_llanto | B112: escena lynde_visita (una opción) | C112: escena resp_spencer_lynde_llanto, hito humillada
A113: lynde_visita | B113: escena lynde_visita | C113: charla par:lynde+marilla:0, charla par:ana+lynde:0, charla par:ana+lynde:1, charla par:ana+lynde+marilla:0, una frase de lynde, noticia ana_lengua, hito humillada
A114: marilla | C114: escena marilla_sabe_camison, escena marilla_sabe_camison_descalza, escena geranio_sola
A115: marilla_doblo_ropa | B115: código | D115: nadie lo lee
A116: marilla_sabe_camison | C116: escena marilla_sabe_camison_descalza
A117: matthew_en_estacion | B117: código | C117: escena estacion
A118: matthew_llego_casa | B118: código | C118: escena tejas_verdes (alternativa)
A119: nombra_avenida | C119: escena conv_matthew_nombres
A120: nombre_propio_ | B120: código | D120: nadie lo lee
A121: nombro_ | B121: código | D121: nadie lo lee
A122: nombro_avenida | B122: escena nombra_avenida | C122: escena conv_matthew_nombres
A123: nombro_burbuja | B123: escena conv_diana_nombres | D123: nadie lo lee
A124: nombro_cerezo | B124: escena primera_gwin | D124: nadie lo lee
A125: nombro_geranio | B125: escena primera_geranio, escena geranio_sola | C125: escena geranio_sola
A126: nombro_lago | B126: escena lago | C126: escena conv_matthew_nombres
A127: nombro_senda | B127: escena conv_diana_nombres | D127: nadie lo lee
A128: ofendio_lynde | B128: escena lynde_visita (una opción) | C128: escena lynde_disculpa, escena conv_lynde_ventana, escena conv_lynde_pelo, escena conv_lynde_queens, charla par:ana+lynde:0, charla par:ana+lynde:1, charla par:ana+lynde+marilla:0, una frase de lynde, noticia ana_lengua
A129: paces | C129: escena conv_gilbert_caramelo
A130: pastel_linimento | B130: escena pastel_linimento | C130: meta allan
A131: perdon_pedido | B131: escena lynde_perdon_marilla | C131: escena lynde_perdon_marilla
A132: perdonada | B132: escena crup_salva | C132: escena ventana_perdonada, escena conv_barry_cordial, una frase de barry, una frase de minnie, una frase de maryjoe, una frase de medico, hito amistad_a_prueba
A133: pide_amiga | B133: código | C133: código
A134: primera_bed | C134: escena primera_noche_sube
A135: primera_noche | B135: escena inicio_llegada, escena primera_noche | C135: escena primera_noche
A136: prohibida | B136: escena prohibida | C136: escena prohibida, escena crup_salva, escena cama_josephine, escena ventana_diana, escena banco_lago_diana, escena pupitre_diana, escena lugar_puente_diana, escena conv_marilla_diana, escena conv_diana_pelo, escena conv_diana_minnie, escena conv_diana_nombres, escena conv_diana_escuela, escena conv_diana_bosque, escena conv_diana_vestidos, escena conv_diana_club, escena conv_diana_gilbert, escena conv_diana_gilbert_contesta, escena conv_diana_tia, escena conv_diana_secreto, escena conv_diana_futuro, escena conv_diana_casarse, escena conv_diana_vela, escena conv_barry_diana, charla par:ana+diana+marilla:1, dichos de paseo_fin_tarde, dichos de paseo_fin, dichos de paseo_si, dichos de mira:diana:flores, dichos de mira:diana:lago, dichos de te_diana:primera, dichos de te_diana_otra_vez, dichos de te_diana_cordial, una frase de diana, una frase de barry, meta picnic, meta te_diana, meta josephine, meta club, meta remo, meta techo, código
A137: queens | B137: escena examen_primera, escena examen_entra | C137: escena ventana_queens, escena faro_queens, charla par:ana+gilbert:1
...

Sheet Metas
A1: Grupo | B1: Meta | C1: Qué es | D1: Requiere | E1: Pista
A2: El comienzo | B2: quedarse | C2: Quedarse en Tejas Verdes | E2: Marilla esperaba un niño. Mañana la lleva a White Sands, donde la Sra. Spencer, a devolverla. Ayúdala, pórtate bien: todavía puede cambiar de opinión.
A3: Amistades | B3: conocer_diana | C3: Conocer a Diana Barry | D3: hecho:se_queda | E3: Quizás Marilla sepa de alguna niña de tu edad. Habla con ella.
A4: Amistades | B4: amigas | C4: Tener una amiga del alma | D4: conocer_diana | E4: Una amistad así se jura, en el jardín, tomadas de las manos.
A5: Amistades | B5: picnic | C5: Ir de picnic con Diana | D5: amigas, hecho:broche, !hecho:prohibida | E5: Al lago, con una canasta. Primero hay que pedirle permiso a Marilla.
A6: Amistades | B6: te_diana | C6: Invitar a Diana a tomar el té | D6: amigas, dias_desde:conocidas_diana:5, afecto:diana:ana>=5, !hecho:prohibida | E6: En Tejas Verdes, con el cordial de frambuesa de Marilla. Invítala cuando la veas.
A7: Amistades | B7: perdon_barry | C7: Recuperar la amistad de los Barry | D7: quedarse, hecho:diana_borracha | E7: La Sra. Barry no quiere que Diana te vea. Solo algo muy grande podría hacerla cambiar de idea.
A8: Amistades | B8: josephine | C8: Hacerse amiga de la tía Josephine | D8: amigas, dias_desde:conocidas_diana:15, afecto:diana:ana>=5, letras:ana>=10, !hecho:prohibida | E8: La tía de la Sra. Barry viene de Charlottetown. Un concierto, una noche en casa de Diana… y una cama de huéspedes.
A9: Amistades | B9: lynde | C9: Visitar a la Sra. Lynde | D9: quedarse | E9: Vive en la Hondonada, junto al camino; desde su ventana lo ve todo. Por la tarde está en casa.
A10: Amistades | B10: allan | C10: Tomar el té con la Sra. Allan | D10: escuela_dominical, hecho:pastel_linimento | E10: La esposa del pastor vive en la casa parroquial, cerca de la iglesia. A veces invita a tomar el té.
A11: En Tejas Verdes | B11: quehaceres | C11: Ayudar con los quehaceres | E11: Lavar los platos, barrer… Marilla los pide, y se notan.
A12: En Tejas Verdes | B12: regalo | C12: Hacerle un regalo a Marilla que le guste | D12: quedarse | E12: A Marilla le gusta lo hecho a mano. Las flores de la huerta también alegran.
A13: En Tejas Verdes | B13: huerta | C13: Sembrar y regar la huerta | E13: Los canteros junto a la casa, con semillas y la regadera de la bomba.
A14: En Tejas Verdes | B14: rezo | C14: Decir sus oraciones | E14: Junto a su cama, en la pieza del alero.
A15: La escuela y los libros | B15: escuela_dominical | C15: Ir a la escuela dominical | D15: quedarse | E15: En la iglesia, camino a Bright River.
A16: La escuela y los libros | B16: escuela | C16: Ir a la escuela | D16: quedarse | E16: La escuela está junto al río, más allá de la aldea. Allí van Diana, Gilbert Blythe y los demás.
A17: La escuela y los libros | B17: recito | C17: Recitar la lección en la escuela | D17: escuela | E17: Hay que estudiarla antes.
A18: La escuela y los libros | B18: queens | C18: Entrar a Queen's | D18: escuela | E18: El examen de ingreso es en Charlottetown, el primer día del verano, desde el segundo año (faltan {dias_examen} días). Se prepara yendo a clases y estudiando la lección: llevas {estudio} días de estudio.
A19: La escuela y los libros | B19: paces | C19: Hacer las paces con Gilbert Blythe | D19: quedarse, hecho:zanahorias, dias_desde:zanahorias:28, estudio:ana>=30 | E19: Le dijo «zanahorias». Él quiere disculparse… si Ana lo deja.
A20: La escuela y los libros | B20: leido | C20: Leer un libro de principio a fin | D20: quedarse | E20: Diana presta libros. Un buen rincón: la silla junto a la ventana de la cocina.
A21: La escuela y los libros | B21: carta | C21: Escribir una carta y mandarla | D21: quedarse | E21: Se escribe en el escritorio de su pieza; el correo está en la tienda de Lawson.
A22: La escuela y los libros | B22: club | C22: Escribir un cuento para el club de cuentos | D22: amigas, !hecho:prohibida | E22: Una historia trágica, con una dama de cabellos de oro… y leérsela a Diana.
A23: La escuela y los libros | B23: concierto | C23: Recitar en el concierto | D23: escuela | E23: En el salón del pueblo, en la aldea. Conviene ensayar.
A24: La escuela y los libros | B24: sala | C24: Decorar el salón para el concierto | D24: escuela | E24: Con flores de la huerta.
A25: Al aire libre | B25: nombres | C25: Ponerle nombre a tres lugares | E25: Hay lugares que se merecen un nombre más bonito que el que tienen.
A26: Al aire libre | B26: sombrero | C26: Adornar su sombrero con flores | D26: quedarse | E26: Con un ramo de la huerta (Marilla no lo va a aprobar).
A27: Al aire libre | B27: remo | C27: Remar en el Lago de las Aguas Brillantes | D27: amigas, !hecho:prohibida | E27: El bote de los Barry está en el lago. En verano.
A28: Al aire libre | B28: patinar | C28: Patinar en el lago helado | D28: quedarse | E28: Solo en invierno.
A29: Al aire libre | B29: trineo | C29: Tirarse en trineo colina abajo | D29: quedarse | E29: Solo en invierno, en la colina.
A30: Travesuras | B30: tinte | C30: Teñirse el pelo de negro azabache | D30: quedarse | E30: El buhonero vende un tinte que promete maravillas… y acepta huevos.
A31: Travesuras | B31: pelo_corto | C31: Librarse del pelo verde | D31: tinte | E31: El tinte no sale con nada. Marilla sabe lo que hay que hacer, aunque a Ana no le va a gustar.
A32: Travesuras | B32: techo | C32: Aceptar el desafío de Josie Pye | D32: amigas, !hecho:prohibida | E32: Caminar por el caballete del techo de los Barry. ¿Qué podría salir mal?
